{"solve_details":{"32":{"NOT_A_NUM":null,"best_bound":84.0,"columns":311,"deterministic_time":493.2195606232,"dettime":493.2195606232,"gap":0.0,"mip_relative_gap":0.0,"nb_iterations":2628,"nb_linear_nonzeros":1259,"nb_nodes_processed":34,"problem_type":"MILP","quality_metrics":{},"status":"integer optimal solution","status_code":101,"time":0.453},"113":{"NOT_A_NUM":null,"best_bound":84.0,"columns":311,"deterministic_time":493.2195606232,"dettime":493.2195606232,"gap":0.0,"mip_relative_gap":0.0,"nb_iterations":2628,"nb_linear_nonzeros":1259,"nb_nodes_processed":34,"problem_type":"MILP","quality_metrics":{},"status":"integer optimal solution","status_code":101,"time":0.453},"38":{"NOT_A_NUM":null,"best_bound":84.0,"columns":311,"deterministic_time":493.2195606232,"dettime":493.2195606232,"gap":0.0,"mip_relative_gap":0.0,"nb_iterations":2628,"nb_linear_nonzeros":1259,"nb_nodes_processed":34,"problem_type":"MILP","quality_metrics":{},"status":"integer optimal solution","status_code":101,"time":0.469},"122":{"NOT_A_NUM":null,"best_bound":84.0,"columns":311,"deterministic_time":493.2195606232,"dettime":493.2195606232,"gap":0.0,"mip_relative_gap":0.0,"nb_iterations":2628,"nb_linear_nonzeros":1259,"nb_nodes_processed":34,"problem_type":"MILP","quality_metrics":{},"status":"integer optimal solution","status_code":101,"time":0.453},"44":{"NOT_A_NUM":null,"best_bound":84.0,"columns":311,"deterministic_time":493.2195606232,"dettime":493.2195606232,"gap":0.0,"mip_relative_gap":0.0,"nb_iterations":2628,"nb_linear_nonzeros":1259,"nb_nodes_processed":34,"problem_type":"MILP","quality_metrics":{},"status":"integer optimal solution","status_code":101,"time":0.453},"29":{"NOT_A_NUM":null,"best_bound":84.0,"columns":311,"deterministic_time":493.2195606232,"dettime":493.2195606232,"gap":0.0,"mip_relative_gap":0.0,"nb_iterations":2628,"nb_linear_nonzeros":1259,"nb_nodes_processed":34,"problem_type":"MILP","quality_metrics":{},"status":"integer optimal solution","status_code":101,"time":0.453},"41":{"NOT_A_NUM":null,"best_bound":84.0,"columns":311,"deterministic_time":493.2195606232,"dettime":493.2195606232,"gap":0.0,"mip_relative_gap":0.0,"nb_iterations":2628,"nb_linear_nonzeros":1259,"nb_nodes_processed":34,"problem_type":"MILP","quality_metrics":{},"status":"integer optimal solution","status_code":101,"time":0.453},"35":{"NOT_A_NUM":null,"best_bound":84.0,"columns":311,"deterministic_time":493.2195606232,"dettime":493.2195606232,"gap":0.0,"mip_relative_gap":0.0,"nb_iterations":2628,"nb_linear_nonzeros":1259,"nb_nodes_processed":34,"problem_type":"MILP","quality_metrics":{},"status":"integer optimal solution","status_code":101,"time":0.454},"125":{"NOT_A_NUM":null,"best_bound":84.0,"columns":311,"deterministic_time":493.2195606232,"dettime":493.2195606232,"gap":0.0,"mip_relative_gap":0.0,"nb_iterations":2628,"nb_linear_nonzeros":1259,"nb_nodes_processed":34,"problem_type":"MILP","quality_metrics":{},"status":"integer optimal solution","status_code":101,"time":0.453},"119":{"NOT_A_NUM":null,"best_bound":84.0,"columns":311,"deterministic_time":493.2195606232,"dettime":493.2195606232,"gap":0.0,"mip_relative_gap":0.0,"nb_iterations":2628,"nb_linear_nonzeros":1259,"nb_nodes_processed":34,"problem_type":"MILP","quality_metrics":{},"status":"integer optimal solution","status_code":101,"time":0.453},"110":{"NOT_A_NUM":null,"best_bound":84.0,"columns":311,"deterministic_time":493.2195606232,"dettime":493.2195606232,"gap":0.0,"mip_relative_gap":0.0,"nb_iterations":2628,"nb_linear_nonzeros":1259,"nb_nodes_processed":34,"problem_type":"MILP","quality_metrics":{},"status":"integer optimal solution","status_code":101,"time":0.453},"116":{"NOT_A_NUM":null,"best_bound":84.0,"columns":311,"deterministic_time":493.2195606232,"dettime":493.2195606232,"gap":0.0,"mip_relative_gap":0.0,"nb_iterations":2628,"nb_linear_nonzeros":1259,"nb_nodes_processed":34,"problem_type":"MILP","quality_metrics":{},"status":"integer optimal solution","status_code":101,"time":0.453},"118":{"NOT_A_NUM":null,"best_bound":84.0,"columns":311,"deterministic_time":503.6641168594,"dettime":503.6641168594,"gap":0.0,"mip_relative_gap":0.0,"nb_iterations":2886,"nb_linear_nonzeros":1259,"nb_nodes_processed":44,"problem_type":"MILP","quality_metrics":{},"status":"integer optimal solution","status_code":101,"time":0.469},"33":{"NOT_A_NUM":null,"best_bound":84.0,"columns":311,"deterministic_time":503.648604393,"dettime":503.648604393,"gap":0.0,"mip_relative_gap":0.0,"nb_iterations":2886,"nb_linear_nonzeros":1259,"nb_nodes_processed":44,"problem_type":"MILP","quality_metrics":{},"status":"integer optimal solution","status_code":101,"time":0.453},"42":{"NOT_A_NUM":null,"best_bound":84.0,"columns":311,"deterministic_time":503.648604393,"dettime":503.648604393,"gap":0.0,"mip_relative_gap":0.0,"nb_iterations":2886,"nb_linear_nonzeros":1259,"nb_nodes_processed":44,"problem_type":"MILP","quality_metrics":{},"status":"integer optimal solution","status_code":101,"time":0.468},"121":{"NOT_A_NUM":null,"best_bound":84.0,"columns":311,"deterministic_time":503.6641168594,"dettime":503.6641168594,"gap":0.0,"mip_relative_gap":0.0,"nb_iterations":2886,"nb_linear_nonzeros":1259,"nb_nodes_processed":44,"problem_type":"MILP","quality_metrics":{},"status":"integer optimal solution","status_code":101,"time":0.453},"39":{"NOT_A_NUM":null,"best_bound":84.0,"columns":311,"deterministic_time":503.648604393,"dettime":503.648604393,"gap":0.0,"mip_relative_gap":0.0,"nb_iterations":2886,"nb_linear_nonzeros":1259,"nb_nodes_processed":44,"problem_type":"MILP","quality_metrics":{},"status":"integer optimal solution","status_code":101,"time":0.453},"36":{"NOT_A_NUM":null,"best_bound":84.0,"columns":311,"deterministic_time":503.648604393,"dettime":503.648604393,"gap":0.0,"mip_relative_gap":0.0,"nb_iterations":2886,"nb_linear_nonzeros":1259,"nb_nodes_processed":44,"problem_type":"MILP","quality_metrics":{},"status":"integer optimal solution","status_code":101,"time":0.469},"37":{"NOT_A_NUM":null,"best_bound":84.0,"columns":311,"deterministic_time":503.6641168594,"dettime":503.6641168594,"gap":0.0,"mip_relative_gap":0.0,"nb_iterations":2886,"nb_linear_nonzeros":1259,"nb_nodes_processed":44,"problem_type":"MILP","quality_metrics":{},"status":"integer optimal solution","status_code":101,"time":0.469},"27":{"NOT_A_NUM":null,"best_bound":84.0,"columns":311,"deterministic_time":503.648604393,"dettime":503.648604393,"gap":0.0,"mip_relative_gap":0.0,"nb_iterations":2886,"nb_linear_nonzeros":1259,"nb_nodes_processed":44,"problem_type":"MILP","quality_metrics":{},"status":"integer optimal solution","status_code":101,"time":0.469},"115":{"NOT_A_NUM":null,"best_bound":84.0,"columns":311,"deterministic_time":503.6641168594,"dettime":503.6641168594,"gap":0.0,"mip_relative_gap":0.0,"nb_iterations":2886,"nb_linear_nonzeros":1259,"nb_nodes_processed":44,"problem_type":"MILP","quality_metrics":{},"status":"integer optimal solution","status_code":101,"time":0.469},"112":{"NOT_A_NUM":null,"best_bound":84.0,"columns":311,"deterministic_time":503.6641168594,"dettime":503.6641168594,"gap":0.0,"mip_relative_gap":0.0,"nb_iterations":2886,"nb_linear_nonzeros":1259,"nb_nodes_processed":44,"problem_type":"MILP","quality_metrics":{},"status":"integer optimal solution","status_code":101,"time":0.469},"111":{"NOT_A_NUM":null,"best_bound":84.0,"columns":311,"deterministic_time":503.648604393,"dettime":503.648604393,"gap":0.0,"mip_relative_gap":0.0,"nb_iterations":2886,"nb_linear_nonzeros":1259,"nb_nodes_processed":44,"problem_type":"MILP","quality_metrics":{},"status":"integer optimal solution","status_code":101,"time":0.5},"28":{"NOT_A_NUM":null,"best_bound":84.0,"columns":311,"deterministic_time":503.6641168594,"dettime":503.6641168594,"gap":0.0,"mip_relative_gap":0.0,"nb_iterations":2886,"nb_linear_nonzeros":1259,"nb_nodes_processed":44,"problem_type":"MILP","quality_metrics":{},"status":"integer optimal solution","status_code":101,"time":0.469},"34":{"NOT_A_NUM":null,"best_bound":84.0,"columns":311,"deterministic_time":503.6641168594,"dettime":503.6641168594,"gap":0.0,"mip_relative_gap":0.0,"nb_iterations":2886,"nb_linear_nonzeros":1259,"nb_nodes_processed":44,"problem_type":"MILP","quality_metrics":{},"status":"integer optimal solution","status_code":101,"time":0.469},"40":{"NOT_A_NUM":null,"best_bound":84.0,"columns":311,"deterministic_time":503.6641168594,"dettime":503.6641168594,"gap":0.0,"mip_relative_gap":0.0,"nb_iterations":2886,"nb_linear_nonzeros":1259,"nb_nodes_processed":44,"problem_type":"MILP","quality_metrics":{},"status":"integer optimal solution","status_code":101,"time":0.468},"124":{"NOT_A_NUM":null,"best_bound":84.0,"columns":311,"deterministic_time":503.6641168594,"dettime":503.6641168594,"gap":0.0,"mip_relative_gap":0.0,"nb_iterations":2886,"nb_linear_nonzeros":1259,"nb_nodes_processed":44,"problem_type":"MILP","quality_metrics":{},"status":"integer optimal solution","status_code":101,"time":0.468},"123":{"NOT_A_NUM":null,"best_bound":84.0,"columns":311,"deterministic_time":503.648604393,"dettime":503.648604393,"gap":0.0,"mip_relative_gap":0.0,"nb_iterations":2886,"nb_linear_nonzeros":1259,"nb_nodes_processed":44,"problem_type":"MILP","quality_metrics":{},"status":"integer optimal solution","status_code":101,"time":0.453},"120":{"NOT_A_NUM":null,"best_bound":84.0,"columns":311,"deterministic_time":503.648604393,"dettime":503.648604393,"gap":0.0,"mip_relative_gap":0.0,"nb_iterations":2886,"nb_linear_nonzeros":1259,"nb_nodes_processed":44,"problem_type":"MILP","quality_metrics":{},"status":"integer optimal solution","status_code":101,"time":0.469},"30":{"NOT_A_NUM":null,"best_bound":84.0,"columns":311,"deterministic_time":503.648604393,"dettime":503.648604393,"gap":0.0,"mip_relative_gap":0.0,"nb_iterations":2886,"nb_linear_nonzeros":1259,"nb_nodes_processed":44,"problem_type":"MILP","quality_metrics":{},"status":"integer optimal solution","status_code":101,"time":0.453},"114":{"NOT_A_NUM":null,"best_bound":84.0,"columns":311,"deterministic_time":503.648604393,"dettime":503.648604393,"gap":0.0,"mip_relative_gap":0.0,"nb_iterations":2886,"nb_linear_nonzeros":1259,"nb_nodes_processed":44,"problem_type":"MILP","quality_metrics":{},"status":"integer optimal solution","status_code":101,"time":0.469},"109":{"NOT_A_NUM":null,"best_bound":84.0,"columns":311,"deterministic_time":503.6641168594,"dettime":503.6641168594,"gap":0.0,"mip_relative_gap":0.0,"nb_iterations":2886,"nb_linear_nonzeros":1259,"nb_nodes_processed":44,"problem_type":"MILP","quality_metrics":{},"status":"integer optimal solution","status_code":101,"time":0.453},"43":{"NOT_A_NUM":null,"best_bound":84.0,"columns":311,"deterministic_time":503.6641168594,"dettime":503.6641168594,"gap":0.0,"mip_relative_gap":0.0,"nb_iterations":2886,"nb_linear_nonzeros":1259,"nb_nodes_processed":44,"problem_type":"MILP","quality_metrics":{},"status":"integer optimal solution","status_code":101,"time":0.469},"31":{"NOT_A_NUM":null,"best_bound":84.0,"columns":311,"deterministic_time":503.6641168594,"dettime":503.6641168594,"gap":0.0,"mip_relative_gap":0.0,"nb_iterations":2886,"nb_linear_nonzeros":1259,"nb_nodes_processed":44,"problem_type":"MILP","quality_metrics":{},"status":"integer optimal solution","status_code":101,"time":0.469},"117":{"NOT_A_NUM":null,"best_bound":84.0,"columns":311,"deterministic_time":503.648604393,"dettime":503.648604393,"gap":0.0,"mip_relative_gap":0.0,"nb_iterations":2886,"nb_linear_nonzeros":1259,"nb_nodes_processed":44,"problem_type":"MILP","quality_metrics":{},"status":"integer optimal solution","status_code":101,"time":0.469},"108":{"NOT_A_NUM":null,"best_bound":84.0,"columns":311,"deterministic_time":503.648604393,"dettime":503.648604393,"gap":0.0,"mip_relative_gap":0.0,"nb_iterations":2886,"nb_linear_nonzeros":1259,"nb_nodes_processed":44,"problem_type":"MILP","quality_metrics":{},"status":"integer optimal solution","status_code":101,"time":0.469},"91":{"NOT_A_NUM":null,"best_bound":84.0,"columns":311,"deterministic_time":541.3815002441,"dettime":541.3815002441,"gap":0.0,"mip_relative_gap":0.0,"nb_iterations":3431,"nb_linear_nonzeros":1259,"nb_nodes_processed":52,"problem_type":"MILP","quality_metrics":{},"status":"integer optimal solution","status_code":101,"time":0.484},"13":{"NOT_A_NUM":null,"best_bound":84.0,"columns":311,"deterministic_time":541.3815002441,"dettime":541.3815002441,"gap":0.0,"mip_relative_gap":0.0,"nb_iterations":3431,"nb_linear_nonzeros":1259,"nb_nodes_processed":52,"problem_type":"MILP","quality_metrics":{},"status":"integer optimal solution","status_code":101,"time":0.485},"88":{"NOT_A_NUM":null,"best_bound":84.0,"columns":311,"deterministic_time":541.3815002441,"dettime":541.3815002441,"gap":0.0,"mip_relative_gap":0.0,"nb_iterations":3431,"nb_linear_nonzeros":1259,"nb_nodes_processed":52,"problem_type":"MILP","quality_metrics":{},"status":"integer optimal solution","status_code":101,"time":0.484},"82":{"NOT_A_NUM":null,"best_bound":84.0,"columns":311,"deterministic_time":541.3815002441,"dettime":541.3815002441,"gap":0.0,"mip_relative_gap":0.0,"nb_iterations":3431,"nb_linear_nonzeros":1259,"nb_nodes_processed":52,"problem_type":"MILP","quality_metrics":{},"status":"integer optimal solution","status_code":101,"time":0.485},"84":{"NOT_A_NUM":null,"best_bound":84.0,"columns":311,"deterministic_time":541.3484792709,"dettime":541.3484792709,"gap":0.0,"mip_relative_gap":0.0,"nb_iterations":3431,"nb_linear_nonzeros":1259,"nb_nodes_processed":52,"problem_type":"MILP","quality_metrics":{},"status":"integer optimal solution","status_code":101,"time":0.484},"97":{"NOT_A_NUM":null,"best_bound":84.0,"columns":311,"deterministic_time":541.3815002441,"dettime":541.3815002441,"gap":0.0,"mip_relative_gap":0.0,"nb_iterations":3431,"nb_linear_nonzeros":1259,"nb_nodes_processed":52,"problem_type":"MILP","quality_metrics":{},"status":"integer optimal solution","status_code":101,"time":0.484},"93":{"NOT_A_NUM":null,"best_bound":84.0,"columns":311,"deterministic_time":541.3484792709,"dettime":541.3484792709,"gap":0.0,"mip_relative_gap":0.0,"nb_iterations":3431,"nb_linear_nonzeros":1259,"nb_nodes_processed":52,"problem_type":"MILP","quality_metrics":{},"status":"integer optimal solution","status_code":101,"time":0.484},"12":{"NOT_A_NUM":null,"best_bound":84.0,"columns":311,"deterministic_time":541.3484792709,"dettime":541.3484792709,"gap":0.0,"mip_relative_gap":0.0,"nb_iterations":3431,"nb_linear_nonzeros":1259,"nb_nodes_processed":52,"problem_type":"MILP","quality_metrics":{},"status":"integer optimal solution","status_code":101,"time":0.485},"81":{"NOT_A_NUM":null,"best_bound":84.0,"columns":311,"deterministic_time":541.3484792709,"dettime":541.3484792709,"gap":0.0,"mip_relative_gap":0.0,"nb_iterations":3431,"nb_linear_nonzeros":1259,"nb_nodes_processed":52,"problem_type":"MILP","quality_metrics":{},"status":"integer optimal solution","status_code":101,"time":0.469},"85":{"NOT_A_NUM":null,"best_bound":84.0,"columns":311,"deterministic_time":541.3815002441,"dettime":541.3815002441,"gap":0.0,"mip_relative_gap":0.0,"nb_iterations":3431,"nb_linear_nonzeros":1259,"nb_nodes_processed":52,"problem_type":"MILP","quality_metrics":{},"status":"integer optimal solution","status_code":101,"time":0.485},"10":{"NOT_A_NUM":null,"best_bound":84.0,"columns":311,"deterministic_time":541.3815002441,"dettime":541.3815002441,"gap":0.0,"mip_relative_gap":0.0,"nb_iterations":3431,"nb_linear_nonzeros":1259,"nb_nodes_processed":52,"problem_type":"MILP","quality_metrics":{},"status":"integer optimal solution","status_code":101,"time":0.469},"16":{"NOT_A_NUM":null,"best_bound":84.0,"columns":311,"deterministic_time":541.3815002441,"dettime":541.3815002441,"gap":0.0,"mip_relative_gap":0.0,"nb_iterations":3431,"nb_linear_nonzeros":1259,"nb_nodes_processed":52,"problem_type":"MILP","quality_metrics":{},"status":"integer optimal solution","status_code":101,"time":0.484},"96":{"NOT_A_NUM":null,"best_bound":84.0,"columns":311,"deterministic_time":541.3484792709,"dettime":541.3484792709,"gap":0.0,"mip_relative_gap":0.0,"nb_iterations":3431,"nb_linear_nonzeros":1259,"nb_nodes_processed":52,"problem_type":"MILP","quality_metrics":{},"status":"integer optimal solution","status_code":101,"time":0.484},"94":{"NOT_A_NUM":null,"best_bound":84.0,"columns":311,"deterministic_time":541.3815002441,"dettime":541.3815002441,"gap":0.0,"mip_relative_gap":0.0,"nb_iterations":3431,"nb_linear_nonzeros":1259,"nb_nodes_processed":52,"problem_type":"MILP","quality_metrics":{},"status":"integer optimal solution","status_code":101,"time":0.484},"90":{"NOT_A_NUM":null,"best_bound":84.0,"columns":311,"deterministic_time":541.3484792709,"dettime":541.3484792709,"gap":0.0,"mip_relative_gap":0.0,"nb_iterations":3431,"nb_linear_nonzeros":1259,"nb_nodes_processed":52,"problem_type":"MILP","quality_metrics":{},"status":"integer optimal solution","status_code":101,"time":0.484},"15":{"NOT_A_NUM":null,"best_bound":84.0,"columns":311,"deterministic_time":541.3484792709,"dettime":541.3484792709,"gap":0.0,"mip_relative_gap":0.0,"nb_iterations":3431,"nb_linear_nonzeros":1259,"nb_nodes_processed":52,"problem_type":"MILP","quality_metrics":{},"status":"integer optimal solution","status_code":101,"time":0.5},"7":{"NOT_A_NUM":null,"best_bound":84.0,"columns":311,"deterministic_time":541.3815002441,"dettime":541.3815002441,"gap":0.0,"mip_relative_gap":0.0,"nb_iterations":3431,"nb_linear_nonzeros":1259,"nb_nodes_processed":52,"problem_type":"MILP","quality_metrics":{},"status":"integer optimal solution","status_code":101,"time":0.484},"87":{"NOT_A_NUM":null,"best_bound":84.0,"columns":311,"deterministic_time":541.3484792709,"dettime":541.3484792709,"gap":0.0,"mip_relative_gap":0.0,"nb_iterations":3431,"nb_linear_nonzeros":1259,"nb_nodes_processed":52,"problem_type":"MILP","quality_metrics":{},"status":"integer optimal solution","status_code":101,"time":0.5},"9":{"NOT_A_NUM":null,"best_bound":84.0,"columns":311,"deterministic_time":541.3484792709,"dettime":541.3484792709,"gap":0.0,"mip_relative_gap":0.0,"nb_iterations":3431,"nb_linear_nonzeros":1259,"nb_nodes_processed":52,"problem_type":"MILP","quality_metrics":{},"status":"integer optimal solution","status_code":101,"time":0.484},"4":{"NOT_A_NUM":null,"best_bound":84.0,"columns":311,"deterministic_time":541.3815002441,"dettime":541.3815002441,"gap":0.0,"mip_relative_gap":0.0,"nb_iterations":3431,"nb_linear_nonzeros":1259,"nb_nodes_processed":52,"problem_type":"MILP","quality_metrics":{},"status":"integer optimal solution","status_code":101,"time":0.484},"6":{"NOT_A_NUM":null,"best_bound":84.0,"columns":311,"deterministic_time":541.3484792709,"dettime":541.3484792709,"gap":0.0,"mip_relative_gap":0.0,"nb_iterations":3431,"nb_linear_nonzeros":1259,"nb_nodes_processed":52,"problem_type":"MILP","quality_metrics":{},"status":"integer optimal solution","status_code":101,"time":0.515},"1":{"NOT_A_NUM":null,"best_bound":84.0,"columns":311,"deterministic_time":541.3815002441,"dettime":541.3815002441,"gap":0.0,"mip_relative_gap":0.0,"nb_iterations":3431,"nb_linear_nonzeros":1259,"nb_nodes_processed":52,"problem_type":"MILP","quality_metrics":{},"status":"integer optimal solution","status_code":101,"time":0.484},"3":{"NOT_A_NUM":null,"best_bound":84.0,"columns":311,"deterministic_time":541.3484792709,"dettime":541.3484792709,"gap":0.0,"mip_relative_gap":0.0,"nb_iterations":3431,"nb_linear_nonzeros":1259,"nb_nodes_processed":52,"problem_type":"MILP","quality_metrics":{},"status":"integer optimal solution","status_code":101,"time":0.484},"86":{"NOT_A_NUM":null,"best_bound":84.0,"columns":311,"deterministic_time":580.9439229965,"dettime":580.9439229965,"gap":0.0,"mip_relative_gap":0.0,"nb_iterations":4409,"nb_linear_nonzeros":1259,"nb_nodes_processed":77,"problem_type":"MILP","quality_metrics":{},"status":"integer optimal solution","status_code":101,"time":0.532},"2":{"NOT_A_NUM":null,"best_bound":84.0,"columns":311,"deterministic_time":580.9439229965,"dettime":580.9439229965,"gap":0.0,"mip_relative_gap":0.0,"nb_iterations":4409,"nb_linear_nonzeros":1259,"nb_nodes_processed":77,"problem_type":"MILP","quality_metrics":{},"status":"integer optimal solution","status_code":101,"time":0.516},"98":{"NOT_A_NUM":null,"best_bound":84.0,"columns":311,"deterministic_time":580.9439229965,"dettime":580.9439229965,"gap":0.0,"mip_relative_gap":0.0,"nb_iterations":4409,"nb_linear_nonzeros":1259,"nb_nodes_processed":77,"problem_type":"MILP","quality_metrics":{},"status":"integer optimal solution","status_code":101,"time":0.516},"5":{"NOT_A_NUM":null,"best_bound":84.0,"columns":311,"deterministic_time":580.9439229965,"dettime":580.9439229965,"gap":0.0,"mip_relative_gap":0.0,"nb_iterations":4409,"nb_linear_nonzeros":1259,"nb_nodes_processed":77,"problem_type":"MILP","quality_metrics":{},"status":"integer optimal solution","status_code":101,"time":0.516},"17":{"NOT_A_NUM":null,"best_bound":84.0,"columns":311,"deterministic_time":580.9439229965,"dettime":580.9439229965,"gap":0.0,"mip_relative_gap":0.0,"nb_iterations":4409,"nb_linear_nonzeros":1259,"nb_nodes_processed":77,"problem_type":"MILP","quality_metrics":{},"status":"integer optimal solution","status_code":101,"time":0.515},"83":{"NOT_A_NUM":null,"best_bound":84.0,"columns":311,"deterministic_time":580.9439229965,"dettime":580.9439229965,"gap":0.0,"mip_relative_gap":0.0,"nb_iterations":4409,"nb_linear_nonzeros":1259,"nb_nodes_processed":77,"problem_type":"MILP","quality_metrics":{},"status":"integer optimal solution","status_code":101,"time":0.516},"89":{"NOT_A_NUM":null,"best_bound":84.0,"columns":311,"deterministic_time":580.9439229965,"dettime":580.9439229965,"gap":0.0,"mip_relative_gap":0.0,"nb_iterations":4409,"nb_linear_nonzeros":1259,"nb_nodes_processed":77,"problem_type":"MILP","quality_metrics":{},"status":"integer optimal solution","status_code":101,"time":0.515},"95":{"NOT_A_NUM":null,"best_bound":84.0,"columns":311,"deterministic_time":580.9439229965,"dettime":580.9439229965,"gap":0.0,"mip_relative_gap":0.0,"nb_iterations":4409,"nb_linear_nonzeros":1259,"nb_nodes_processed":77,"problem_type":"MILP","quality_metrics":{},"status":"integer optimal solution","status_code":101,"time":0.516},"92":{"NOT_A_NUM":null,"best_bound":84.0,"columns":311,"deterministic_time":580.9439229965,"dettime":580.9439229965,"gap":0.0,"mip_relative_gap":0.0,"nb_iterations":4409,"nb_linear_nonzeros":1259,"nb_nodes_processed":77,"problem_type":"MILP","quality_metrics":{},"status":"integer optimal solution","status_code":101,"time":0.516},"14":{"NOT_A_NUM":null,"best_bound":84.0,"columns":311,"deterministic_time":580.9439229965,"dettime":580.9439229965,"gap":0.0,"mip_relative_gap":0.0,"nb_iterations":4409,"nb_linear_nonzeros":1259,"nb_nodes_processed":77,"problem_type":"MILP","quality_metrics":{},"status":"integer optimal solution","status_code":101,"time":0.531},"11":{"NOT_A_NUM":null,"best_bound":84.0,"columns":311,"deterministic_time":580.9439229965,"dettime":580.9439229965,"gap":0.0,"mip_relative_gap":0.0,"nb_iterations":4409,"nb_linear_nonzeros":1259,"nb_nodes_processed":77,"problem_type":"MILP","quality_metrics":{},"status":"integer optimal solution","status_code":101,"time":0.531},"8":{"NOT_A_NUM":null,"best_bound":84.0,"columns":311,"deterministic_time":580.9439229965,"dettime":580.9439229965,"gap":0.0,"mip_relative_gap":0.0,"nb_iterations":4409,"nb_linear_nonzeros":1259,"nb_nodes_processed":77,"problem_type":"MILP","quality_metrics":{},"status":"integer optimal solution","status_code":101,"time":0.515},"0":{"NOT_A_NUM":null,"best_bound":84.0,"columns":311,"deterministic_time":541.3484792709,"dettime":541.3484792709,"gap":0.0,"mip_relative_gap":0.0,"nb_iterations":3431,"nb_linear_nonzeros":1259,"nb_nodes_processed":52,"problem_type":"MILP","quality_metrics":{},"status":"integer optimal solution","status_code":101,"time":0.485},"71":{"NOT_A_NUM":null,"best_bound":84.0,"columns":311,"deterministic_time":802.9786949158,"dettime":802.9786949158,"gap":0.0,"mip_relative_gap":0.0,"nb_iterations":5461,"nb_linear_nonzeros":1259,"nb_nodes_processed":131,"problem_type":"MILP","quality_metrics":{},"status":"integer optimal solution","status_code":101,"time":0.735},"137":{"NOT_A_NUM":null,"best_bound":84.0,"columns":311,"deterministic_time":802.9786949158,"dettime":802.9786949158,"gap":0.0,"mip_relative_gap":0.0,"nb_iterations":5461,"nb_linear_nonzeros":1259,"nb_nodes_processed":131,"problem_type":"MILP","quality_metrics":{},"status":"integer optimal solution","status_code":101,"time":0.719},"152":{"NOT_A_NUM":null,"best_bound":84.0,"columns":311,"deterministic_time":802.9786949158,"dettime":802.9786949158,"gap":0.0,"mip_relative_gap":0.0,"nb_iterations":5461,"nb_linear_nonzeros":1259,"nb_nodes_processed":131,"problem_type":"MILP","quality_metrics":{},"status":"integer optimal solution","status_code":101,"time":0.703},"65":{"NOT_A_NUM":null,"best_bound":84.0,"columns":311,"deterministic_time":802.9786949158,"dettime":802.9786949158,"gap":0.0,"mip_relative_gap":0.0,"nb_iterations":5461,"nb_linear_nonzeros":1259,"nb_nodes_processed":131,"problem_type":"MILP","quality_metrics":{},"status":"integer optimal solution","status_code":101,"time":0.719},"68":{"NOT_A_NUM":null,"best_bound":84.0,"columns":311,"deterministic_time":802.9786949158,"dettime":802.9786949158,"gap":0.0,"mip_relative_gap":0.0,"nb_iterations":5461,"nb_linear_nonzeros":1259,"nb_nodes_processed":131,"problem_type":"MILP","quality_metrics":{},"status":"integer optimal solution","status_code":101,"time":0.719},"59":{"NOT_A_NUM":null,"best_bound":84.0,"columns":311,"deterministic_time":802.9786949158,"dettime":802.9786949158,"gap":0.0,"mip_relative_gap":0.0,"nb_iterations":5461,"nb_linear_nonzeros":1259,"nb_nodes_processed":131,"problem_type":"MILP","quality_metrics":{},"status":"integer optimal solution","status_code":101,"time":0.719},"140":{"NOT_A_NUM":null,"best_bound":84.0,"columns":311,"deterministic_time":802.9786949158,"dettime":802.9786949158,"gap":0.0,"mip_relative_gap":0.0,"nb_iterations":5461,"nb_linear_nonzeros":1259,"nb_nodes_processed":131,"problem_type":"MILP","quality_metrics":{},"status":"integer optimal solution","status_code":101,"time":0.719},"149":{"NOT_A_NUM":null,"best_bound":84.0,"columns":311,"deterministic_time":802.9786949158,"dettime":802.9786949158,"gap":0.0,"mip_relative_gap":0.0,"nb_iterations":5461,"nb_linear_nonzeros":1259,"nb_nodes_processed":131,"problem_type":"MILP","quality_metrics":{},"status":"integer optimal solution","status_code":101,"time":0.719},"146":{"NOT_A_NUM":null,"best_bound":84.0,"columns":311,"deterministic_time":802.9786949158,"dettime":802.9786949158,"gap":0.0,"mip_relative_gap":0.0,"nb_iterations":5461,"nb_linear_nonzeros":1259,"nb_nodes_processed":131,"problem_type":"MILP","quality_metrics":{},"status":"integer optimal solution","status_code":101,"time":0.735},"56":{"NOT_A_NUM":null,"best_bound":84.0,"columns":311,"deterministic_time":802.9786949158,"dettime":802.9786949158,"gap":0.0,"mip_relative_gap":0.0,"nb_iterations":5461,"nb_linear_nonzeros":1259,"nb_nodes_processed":131,"problem_type":"MILP","quality_metrics":{},"status":"integer optimal solution","status_code":101,"time":0.719},"143":{"NOT_A_NUM":null,"best_bound":84.0,"columns":311,"deterministic_time":802.9786949158,"dettime":802.9786949158,"gap":0.0,"mip_relative_gap":0.0,"nb_iterations":5461,"nb_linear_nonzeros":1259,"nb_nodes_processed":131,"problem_type":"MILP","quality_metrics":{},"status":"integer optimal solution","status_code":101,"time":0.703},"62":{"NOT_A_NUM":null,"best_bound":84.0,"columns":311,"deterministic_time":802.9786949158,"dettime":802.9786949158,"gap":0.0,"mip_relative_gap":0.0,"nb_iterations":5461,"nb_linear_nonzeros":1259,"nb_nodes_processed":131,"problem_type":"MILP","quality_metrics":{},"status":"integer optimal solution","status_code":101,"time":0.735},"63":{"NOT_A_NUM":null,"best_bound":84.0,"columns":311,"deterministic_time":834.4627943039,"dettime":834.4627943039,"gap":0.0,"mip_relative_gap":0.0,"nb_iterations":6168,"nb_linear_nonzeros":1259,"nb_nodes_processed":181,"problem_type":"MILP","quality_metrics":{},"status":"integer optimal solution","status_code":101,"time":0.734},"135":{"NOT_A_NUM":null,"best_bound":84.0,"columns":311,"deterministic_time":834.4627943039,"dettime":834.4627943039,"gap":0.0,"mip_relative_gap":0.0,"nb_iterations":6168,"nb_linear_nonzeros":1259,"nb_nodes_processed":181,"problem_type":"MILP","quality_metrics":{},"status":"integer optimal solution","status_code":101,"time":0.734},"58":{"NOT_A_NUM":null,"best_bound":84.0,"columns":311,"deterministic_time":834.4993581772,"dettime":834.4993581772,"gap":0.0,"mip_relative_gap":0.0,"nb_iterations":6168,"nb_linear_nonzeros":1259,"nb_nodes_processed":181,"problem_type":"MILP","quality_metrics":{},"status":"integer optimal solution","status_code":101,"time":0.734},"148":{"NOT_A_NUM":null,"best_bound":84.0,"columns":311,"deterministic_time":834.4993581772,"dettime":834.4993581772,"gap":0.0,"mip_relative_gap":0.0,"nb_iterations":6168,"nb_linear_nonzeros":1259,"nb_nodes_processed":181,"problem_type":"MILP","quality_metrics":{},"status":"integer optimal solution","status_code":101,"time":0.735},"138":{"NOT_A_NUM":null,"best_bound":84.0,"columns":311,"deterministic_time":834.4627943039,"dettime":834.4627943039,"gap":0.0,"mip_relative_gap":0.0,"nb_iterations":6168,"nb_linear_nonzeros":1259,"nb_nodes_processed":181,"problem_type":"MILP","quality_metrics":{},"status":"integer optimal solution","status_code":101,"time":0.75},"151":{"NOT_A_NUM":null,"best_bound":84.0,"columns":311,"deterministic_time":834.4993581772,"dettime":834.4993581772,"gap":0.0,"mip_relative_gap":0.0,"nb_iterations":6168,"nb_linear_nonzeros":1259,"nb_nodes_processed":181,"problem_type":"MILP","quality_metrics":{},"status":"integer optimal solution","status_code":101,"time":0.735},"64":{"NOT_A_NUM":null,"best_bound":84.0,"columns":311,"deterministic_time":834.4993581772,"dettime":834.4993581772,"gap":0.0,"mip_relative_gap":0.0,"nb_iterations":6168,"nb_linear_nonzeros":1259,"nb_nodes_processed":181,"problem_type":"MILP","quality_metrics":{},"status":"integer optimal solution","status_code":101,"time":0.719},"141":{"NOT_A_NUM":null,"best_bound":84.0,"columns":311,"deterministic_time":834.4627943039,"dettime":834.4627943039,"gap":0.0,"mip_relative_gap":0.0,"nb_iterations":6168,"nb_linear_nonzeros":1259,"nb_nodes_processed":181,"problem_type":"MILP","quality_metrics":{},"status":"integer optimal solution","status_code":101,"time":0.734},"139":{"NOT_A_NUM":null,"best_bound":84.0,"columns":311,"deterministic_time":834.4993581772,"dettime":834.4993581772,"gap":0.0,"mip_relative_gap":0.0,"nb_iterations":6168,"nb_linear_nonzeros":1259,"nb_nodes_processed":181,"problem_type":"MILP","quality_metrics":{},"status":"integer optimal solution","status_code":101,"time":0.735},"54":{"NOT_A_NUM":null,"best_bound":84.0,"columns":311,"deterministic_time":834.4627943039,"dettime":834.4627943039,"gap":0.0,"mip_relative_gap":0.0,"nb_iterations":6168,"nb_linear_nonzeros":1259,"nb_nodes_processed":181,"problem_type":"MILP","quality_metrics":{},"status":"integer optimal solution","status_code":101,"time":0.75},"57":{"NOT_A_NUM":null,"best_bound":84.0,"columns":311,"deterministic_time":834.4627943039,"dettime":834.4627943039,"gap":0.0,"mip_relative_gap":0.0,"nb_iterations":6168,"nb_linear_nonzeros":1259,"nb_nodes_processed":181,"problem_type":"MILP","quality_metrics":{},"status":"integer optimal solution","status_code":101,"time":0.734},"147":{"NOT_A_NUM":null,"best_bound":84.0,"columns":311,"deterministic_time":834.4627943039,"dettime":834.4627943039,"gap":0.0,"mip_relative_gap":0.0,"nb_iterations":6168,"nb_linear_nonzeros":1259,"nb_nodes_processed":181,"problem_type":"MILP","quality_metrics":{},"status":"integer optimal solution","status_code":101,"time":0.75},"69":{"NOT_A_NUM":null,"best_bound":84.0,"columns":311,"deterministic_time":834.4627943039,"dettime":834.4627943039,"gap":0.0,"mip_relative_gap":0.0,"nb_iterations":6168,"nb_linear_nonzeros":1259,"nb_nodes_processed":181,"problem_type":"MILP","quality_metrics":{},"status":"integer optimal solution","status_code":101,"time":0.735},"66":{"NOT_A_NUM":null,"best_bound":84.0,"columns":311,"deterministic_time":834.4627943039,"dettime":834.4627943039,"gap":0.0,"mip_relative_gap":0.0,"nb_iterations":6168,"nb_linear_nonzeros":1259,"nb_nodes_processed":181,"problem_type":"MILP","quality_metrics":{},"status":"integer optimal solution","status_code":101,"time":0.75},"61":{"NOT_A_NUM":null,"best_bound":84.0,"columns":311,"deterministic_time":834.4993581772,"dettime":834.4993581772,"gap":0.0,"mip_relative_gap":0.0,"nb_iterations":6168,"nb_linear_nonzeros":1259,"nb_nodes_processed":181,"problem_type":"MILP","quality_metrics":{},"status":"integer optimal solution","status_code":101,"time":0.734},"144":{"NOT_A_NUM":null,"best_bound":84.0,"columns":311,"deterministic_time":834.4627943039,"dettime":834.4627943039,"gap":0.0,"mip_relative_gap":0.0,"nb_iterations":6168,"nb_linear_nonzeros":1259,"nb_nodes_processed":181,"problem_type":"MILP","quality_metrics":{},"status":"integer optimal solution","status_code":101,"time":0.734},"145":{"NOT_A_NUM":null,"best_bound":84.0,"columns":311,"deterministic_time":834.4993581772,"dettime":834.4993581772,"gap":0.0,"mip_relative_gap":0.0,"nb_iterations":6168,"nb_linear_nonzeros":1259,"nb_nodes_processed":181,"problem_type":"MILP","quality_metrics":{},"status":"integer optimal solution","status_code":101,"time":0.766},"136":{"NOT_A_NUM":null,"best_bound":84.0,"columns":311,"deterministic_time":834.4993581772,"dettime":834.4993581772,"gap":0.0,"mip_relative_gap":0.0,"nb_iterations":6168,"nb_linear_nonzeros":1259,"nb_nodes_processed":181,"problem_type":"MILP","quality_metrics":{},"status":"integer optimal solution","status_code":101,"time":0.734},"67":{"NOT_A_NUM":null,"best_bound":84.0,"columns":311,"deterministic_time":834.4993581772,"dettime":834.4993581772,"gap":0.0,"mip_relative_gap":0.0,"nb_iterations":6168,"nb_linear_nonzeros":1259,"nb_nodes_processed":181,"problem_type":"MILP","quality_metrics":{},"status":"integer optimal solution","status_code":101,"time":0.735},"142":{"NOT_A_NUM":null,"best_bound":84.0,"columns":311,"deterministic_time":834.4993581772,"dettime":834.4993581772,"gap":0.0,"mip_relative_gap":0.0,"nb_iterations":6168,"nb_linear_nonzeros":1259,"nb_nodes_processed":181,"problem_type":"MILP","quality_metrics":{},"status":"integer optimal solution","status_code":101,"time":0.75},"150":{"NOT_A_NUM":null,"best_bound":84.0,"columns":311,"deterministic_time":834.4627943039,"dettime":834.4627943039,"gap":0.0,"mip_relative_gap":0.0,"nb_iterations":6168,"nb_linear_nonzeros":1259,"nb_nodes_processed":181,"problem_type":"MILP","quality_metrics":{},"status":"integer optimal solution","status_code":101,"time":0.734},"60":{"NOT_A_NUM":null,"best_bound":84.0,"columns":311,"deterministic_time":834.4627943039,"dettime":834.4627943039,"gap":0.0,"mip_relative_gap":0.0,"nb_iterations":6168,"nb_linear_nonzeros":1259,"nb_nodes_processed":181,"problem_type":"MILP","quality_metrics":{},"status":"integer optimal solution","status_code":101,"time":0.734},"70":{"NOT_A_NUM":null,"best_bound":84.0,"columns":311,"deterministic_time":834.4993581772,"dettime":834.4993581772,"gap":0.0,"mip_relative_gap":0.0,"nb_iterations":6168,"nb_linear_nonzeros":1259,"nb_nodes_processed":181,"problem_type":"MILP","quality_metrics":{},"status":"integer optimal solution","status_code":101,"time":0.75},"55":{"NOT_A_NUM":null,"best_bound":84.0,"columns":311,"deterministic_time":834.4993581772,"dettime":834.4993581772,"gap":0.0,"mip_relative_gap":0.0,"nb_iterations":6168,"nb_linear_nonzeros":1259,"nb_nodes_processed":181,"problem_type":"MILP","quality_metrics":{},"status":"integer optimal solution","status_code":101,"time":0.734},"77":{"NOT_A_NUM":null,"best_bound":84.0,"columns":311,"deterministic_time":1226.2557239532,"dettime":1226.2557239532,"gap":0.0,"mip_relative_gap":0.0,"nb_iterations":2467,"nb_linear_nonzeros":1259,"nb_nodes_processed":10,"problem_type":"MILP","quality_metrics":{},"status":"integer optimal solution","status_code":101,"time":1.109},"80":{"NOT_A_NUM":null,"best_bound":84.0,"columns":311,"deterministic_time":1226.2557239532,"dettime":1226.2557239532,"gap":0.0,"mip_relative_gap":0.0,"nb_iterations":2467,"nb_linear_nonzeros":1259,"nb_nodes_processed":10,"problem_type":"MILP","quality_metrics":{},"status":"integer optimal solution","status_code":101,"time":1.125},"158":{"NOT_A_NUM":null,"best_bound":84.0,"columns":311,"deterministic_time":1226.2557239532,"dettime":1226.2557239532,"gap":0.0,"mip_relative_gap":0.0,"nb_iterations":2467,"nb_linear_nonzeros":1259,"nb_nodes_processed":10,"problem_type":"MILP","quality_metrics":{},"status":"integer optimal solution","status_code":101,"time":1.11},"74":{"NOT_A_NUM":null,"best_bound":84.0,"columns":311,"deterministic_time":1226.2557239532,"dettime":1226.2557239532,"gap":0.0,"mip_relative_gap":0.0,"nb_iterations":2467,"nb_linear_nonzeros":1259,"nb_nodes_processed":10,"problem_type":"MILP","quality_metrics":{},"status":"integer optimal solution","status_code":101,"time":1.125},"73":{"NOT_A_NUM":null,"best_bound":84.0,"columns":311,"deterministic_time":1235.8678102493,"dettime":1235.8678102493,"gap":0.0,"mip_relative_gap":0.0,"nb_iterations":2633,"nb_linear_nonzeros":1259,"nb_nodes_processed":20,"problem_type":"MILP","quality_metrics":{},"status":"integer optimal solution","status_code":101,"time":1.125},"154":{"NOT_A_NUM":null,"best_bound":84.0,"columns":311,"deterministic_time":1235.8678102493,"dettime":1235.8678102493,"gap":0.0,"mip_relative_gap":0.0,"nb_iterations":2633,"nb_linear_nonzeros":1259,"nb_nodes_processed":20,"problem_type":"MILP","quality_metrics":{},"status":"integer optimal solution","status_code":101,"time":1.141},"76":{"NOT_A_NUM":null,"best_bound":84.0,"columns":311,"deterministic_time":1235.8678102493,"dettime":1235.8678102493,"gap":0.0,"mip_relative_gap":0.0,"nb_iterations":2633,"nb_linear_nonzeros":1259,"nb_nodes_processed":20,"problem_type":"MILP","quality_metrics":{},"status":"integer optimal solution","status_code":101,"time":1.125},"79":{"NOT_A_NUM":null,"best_bound":84.0,"columns":311,"deterministic_time":1235.8678102493,"dettime":1235.8678102493,"gap":0.0,"mip_relative_gap":0.0,"nb_iterations":2633,"nb_linear_nonzeros":1259,"nb_nodes_processed":20,"problem_type":"MILP","quality_metrics":{},"status":"integer optimal solution","status_code":101,"time":1.125},"161":{"NOT_A_NUM":null,"best_bound":84.0,"columns":311,"deterministic_time":1226.2557239532,"dettime":1226.2557239532,"gap":0.0,"mip_relative_gap":0.0,"nb_iterations":2467,"nb_linear_nonzeros":1259,"nb_nodes_processed":10,"problem_type":"MILP","quality_metrics":{},"status":"integer optimal solution","status_code":101,"time":1.125},"155":{"NOT_A_NUM":null,"best_bound":84.0,"columns":311,"deterministic_time":1226.2557239532,"dettime":1226.2557239532,"gap":0.0,"mip_relative_gap":0.0,"nb_iterations":2467,"nb_linear_nonzeros":1259,"nb_nodes_processed":10,"problem_type":"MILP","quality_metrics":{},"status":"integer optimal solution","status_code":101,"time":1.125},"157":{"NOT_A_NUM":null,"best_bound":84.0,"columns":311,"deterministic_time":1235.8678102493,"dettime":1235.8678102493,"gap":0.0,"mip_relative_gap":0.0,"nb_iterations":2633,"nb_linear_nonzeros":1259,"nb_nodes_processed":20,"problem_type":"MILP","quality_metrics":{},"status":"integer optimal solution","status_code":101,"time":1.125},"160":{"NOT_A_NUM":null,"best_bound":84.0,"columns":311,"deterministic_time":1235.8678102493,"dettime":1235.8678102493,"gap":0.0,"mip_relative_gap":0.0,"nb_iterations":2633,"nb_linear_nonzeros":1259,"nb_nodes_processed":20,"problem_type":"MILP","quality_metrics":{},"status":"integer optimal solution","status_code":101,"time":1.14},"99":{"NOT_A_NUM":null,"best_bound":84.0,"columns":311,"deterministic_time":1334.982175827,"dettime":1334.982175827,"gap":0.0,"mip_relative_gap":0.0,"nb_iterations":3615,"nb_linear_nonzeros":1259,"nb_nodes_processed":63,"problem_type":"MILP","quality_metrics":{},"status":"integer optimal solution","status_code":101,"time":1.14},"102":{"NOT_A_NUM":null,"best_bound":84.0,"columns":311,"deterministic_time":1334.982175827,"dettime":1334.982175827,"gap":0.0,"mip_relative_gap":0.0,"nb_iterations":3615,"nb_linear_nonzeros":1259,"nb_nodes_processed":63,"problem_type":"MILP","quality_metrics":{},"status":"integer optimal solution","status_code":101,"time":1.157},"18":{"NOT_A_NUM":null,"best_bound":84.0,"columns":311,"deterministic_time":1334.982175827,"dettime":1334.982175827,"gap":0.0,"mip_relative_gap":0.0,"nb_iterations":3615,"nb_linear_nonzeros":1259,"nb_nodes_processed":63,"problem_type":"MILP","quality_metrics":{},"status":"integer optimal solution","status_code":101,"time":1.156},"24":{"NOT_A_NUM":null,"best_bound":84.0,"columns":311,"deterministic_time":1334.982175827,"dettime":1334.982175827,"gap":0.0,"mip_relative_gap":0.0,"nb_iterations":3615,"nb_linear_nonzeros":1259,"nb_nodes_processed":63,"problem_type":"MILP","quality_metrics":{},"status":"integer optimal solution","status_code":101,"time":1.172},"105":{"NOT_A_NUM":null,"best_bound":84.0,"columns":311,"deterministic_time":1334.982175827,"dettime":1334.982175827,"gap":0.0,"mip_relative_gap":0.0,"nb_iterations":3615,"nb_linear_nonzeros":1259,"nb_nodes_processed":63,"problem_type":"MILP","quality_metrics":{},"status":"integer optimal solution","status_code":101,"time":1.156},"21":{"NOT_A_NUM":null,"best_bound":84.0,"columns":311,"deterministic_time":1334.982175827,"dettime":1334.982175827,"gap":0.0,"mip_relative_gap":0.0,"nb_iterations":3615,"nb_linear_nonzeros":1259,"nb_nodes_processed":63,"problem_type":"MILP","quality_metrics":{},"status":"integer optimal solution","status_code":101,"time":1.156},"72":{"NOT_A_NUM":null,"best_bound":84.0,"columns":311,"deterministic_time":1294.6202306747,"dettime":1294.6202306747,"gap":0.0,"mip_relative_gap":0.0,"nb_iterations":3011,"nb_linear_nonzeros":1259,"nb_nodes_processed":24,"problem_type":"MILP","quality_metrics":{},"status":"integer optimal solution","status_code":101,"time":1.188},"159":{"NOT_A_NUM":null,"best_bound":84.0,"columns":311,"deterministic_time":1294.6202306747,"dettime":1294.6202306747,"gap":0.0,"mip_relative_gap":0.0,"nb_iterations":3011,"nb_linear_nonzeros":1259,"nb_nodes_processed":24,"problem_type":"MILP","quality_metrics":{},"status":"integer optimal solution","status_code":101,"time":1.188},"153":{"NOT_A_NUM":null,"best_bound":84.0,"columns":311,"deterministic_time":1294.6202306747,"dettime":1294.6202306747,"gap":0.0,"mip_relative_gap":0.0,"nb_iterations":3011,"nb_linear_nonzeros":1259,"nb_nodes_processed":24,"problem_type":"MILP","quality_metrics":{},"status":"integer optimal solution","status_code":101,"time":1.187},"156":{"NOT_A_NUM":null,"best_bound":84.0,"columns":311,"deterministic_time":1294.6202306747,"dettime":1294.6202306747,"gap":0.0,"mip_relative_gap":0.0,"nb_iterations":3011,"nb_linear_nonzeros":1259,"nb_nodes_processed":24,"problem_type":"MILP","quality_metrics":{},"status":"integer optimal solution","status_code":101,"time":1.172},"75":{"NOT_A_NUM":null,"best_bound":84.0,"columns":311,"deterministic_time":1294.6202306747,"dettime":1294.6202306747,"gap":0.0,"mip_relative_gap":0.0,"nb_iterations":3011,"nb_linear_nonzeros":1259,"nb_nodes_processed":24,"problem_type":"MILP","quality_metrics":{},"status":"integer optimal solution","status_code":101,"time":1.156},"78":{"NOT_A_NUM":null,"best_bound":84.0,"columns":311,"deterministic_time":1294.6202306747,"dettime":1294.6202306747,"gap":0.0,"mip_relative_gap":0.0,"nb_iterations":3011,"nb_linear_nonzeros":1259,"nb_nodes_processed":24,"problem_type":"MILP","quality_metrics":{},"status":"integer optimal solution","status_code":101,"time":1.172},"104":{"NOT_A_NUM":null,"best_bound":84.0,"columns":311,"deterministic_time":1479.3247003555,"dettime":1479.3247003555,"gap":0.0,"mip_relative_gap":0.0,"nb_iterations":4707,"nb_linear_nonzeros":1259,"nb_nodes_processed":59,"problem_type":"MILP","quality_metrics":{},"status":"integer optimal solution","status_code":101,"time":1.282},"26":{"NOT_A_NUM":null,"best_bound":84.0,"columns":311,"deterministic_time":1479.3247003555,"dettime":1479.3247003555,"gap":0.0,"mip_relative_gap":0.0,"nb_iterations":4707,"nb_linear_nonzeros":1259,"nb_nodes_processed":59,"problem_type":"MILP","quality_metrics":{},"status":"integer optimal solution","status_code":101,"time":1.266},"20":{"NOT_A_NUM":null,"best_bound":84.0,"columns":311,"deterministic_time":1479.3247003555,"dettime":1479.3247003555,"gap":0.0,"mip_relative_gap":0.0,"nb_iterations":4707,"nb_linear_nonzeros":1259,"nb_nodes_processed":59,"problem_type":"MILP","quality_metrics":{},"status":"integer optimal solution","status_code":101,"time":1.281},"101":{"NOT_A_NUM":null,"best_bound":84.0,"columns":311,"deterministic_time":1479.3247003555,"dettime":1479.3247003555,"gap":0.0,"mip_relative_gap":0.0,"nb_iterations":4707,"nb_linear_nonzeros":1259,"nb_nodes_processed":59,"problem_type":"MILP","quality_metrics":{},"status":"integer optimal solution","status_code":101,"time":1.282},"107":{"NOT_A_NUM":null,"best_bound":84.0,"columns":311,"deterministic_time":1479.3247003555,"dettime":1479.3247003555,"gap":0.0,"mip_relative_gap":0.0,"nb_iterations":4707,"nb_linear_nonzeros":1259,"nb_nodes_processed":59,"problem_type":"MILP","quality_metrics":{},"status":"integer optimal solution","status_code":101,"time":1.297},"23":{"NOT_A_NUM":null,"best_bound":84.0,"columns":311,"deterministic_time":1479.3247003555,"dettime":1479.3247003555,"gap":0.0,"mip_relative_gap":0.0,"nb_iterations":4707,"nb_linear_nonzeros":1259,"nb_nodes_processed":59,"problem_type":"MILP","quality_metrics":{},"status":"integer optimal solution","status_code":101,"time":1.265},"19":{"NOT_A_NUM":null,"best_bound":84.0,"columns":311,"deterministic_time":1506.209107399,"dettime":1506.209107399,"gap":0.0,"mip_relative_gap":0.0,"nb_iterations":5179,"nb_linear_nonzeros":1259,"nb_nodes_processed":88,"problem_type":"MILP","quality_metrics":{},"status":"integer optimal solution","status_code":101,"time":1.265},"22":{"NOT_A_NUM":null,"best_bound":84.0,"columns":311,"deterministic_time":1506.209107399,"dettime":1506.209107399,"gap":0.0,"mip_relative_gap":0.0,"nb_iterations":5179,"nb_linear_nonzeros":1259,"nb_nodes_processed":88,"problem_type":"MILP","quality_metrics":{},"status":"integer optimal solution","status_code":101,"time":1.282},"103":{"NOT_A_NUM":null,"best_bound":84.0,"columns":311,"deterministic_time":1506.209107399,"dettime":1506.209107399,"gap":0.0,"mip_relative_gap":0.0,"nb_iterations":5179,"nb_linear_nonzeros":1259,"nb_nodes_processed":88,"problem_type":"MILP","quality_metrics":{},"status":"integer optimal solution","status_code":101,"time":1.281},"100":{"NOT_A_NUM":null,"best_bound":84.0,"columns":311,"deterministic_time":1506.209107399,"dettime":1506.209107399,"gap":0.0,"mip_relative_gap":0.0,"nb_iterations":5179,"nb_linear_nonzeros":1259,"nb_nodes_processed":88,"problem_type":"MILP","quality_metrics":{},"status":"integer optimal solution","status_code":101,"time":1.281},"106":{"NOT_A_NUM":null,"best_bound":84.0,"columns":311,"deterministic_time":1506.209107399,"dettime":1506.209107399,"gap":0.0,"mip_relative_gap":0.0,"nb_iterations":5179,"nb_linear_nonzeros":1259,"nb_nodes_processed":88,"problem_type":"MILP","quality_metrics":{},"status":"integer optimal solution","status_code":101,"time":1.281},"25":{"NOT_A_NUM":null,"best_bound":84.0,"columns":311,"deterministic_time":1506.209107399,"dettime":1506.209107399,"gap":0.0,"mip_relative_gap":0.0,"nb_iterations":5179,"nb_linear_nonzeros":1259,"nb_nodes_processed":88,"problem_type":"MILP","quality_metrics":{},"status":"integer optimal solution","status_code":101,"time":1.328},"134":{"NOT_A_NUM":null,"best_bound":84.0,"columns":311,"deterministic_time":1529.1573791504,"dettime":1529.1573791504,"gap":0.0,"mip_relative_gap":0.0,"nb_iterations":4807,"nb_linear_nonzeros":1259,"nb_nodes_processed":95,"problem_type":"MILP","quality_metrics":{},"status":"integer optimal solution","status_code":101,"time":1.312},"53":{"NOT_A_NUM":null,"best_bound":84.0,"columns":311,"deterministic_time":1529.1573791504,"dettime":1529.1573791504,"gap":0.0,"mip_relative_gap":0.0,"nb_iterations":4807,"nb_linear_nonzeros":1259,"nb_nodes_processed":95,"problem_type":"MILP","quality_metrics":{},"status":"integer optimal solution","status_code":101,"time":1.344},"131":{"NOT_A_NUM":null,"best_bound":84.0,"columns":311,"deterministic_time":1529.1573791504,"dettime":1529.1573791504,"gap":0.0,"mip_relative_gap":0.0,"nb_iterations":4807,"nb_linear_nonzeros":1259,"nb_nodes_processed":95,"problem_type":"MILP","quality_metrics":{},"status":"integer optimal solution","status_code":101,"time":1.328},"47":{"NOT_A_NUM":null,"best_bound":84.0,"columns":311,"deterministic_time":1529.1573791504,"dettime":1529.1573791504,"gap":0.0,"mip_relative_gap":0.0,"nb_iterations":4807,"nb_linear_nonzeros":1259,"nb_nodes_processed":95,"problem_type":"MILP","quality_metrics":{},"status":"integer optimal solution","status_code":101,"time":1.313},"50":{"NOT_A_NUM":null,"best_bound":84.0,"columns":311,"deterministic_time":1529.1573791504,"dettime":1529.1573791504,"gap":0.0,"mip_relative_gap":0.0,"nb_iterations":4807,"nb_linear_nonzeros":1259,"nb_nodes_processed":95,"problem_type":"MILP","quality_metrics":{},"status":"integer optimal solution","status_code":101,"time":1.312},"128":{"NOT_A_NUM":null,"best_bound":84.0,"columns":311,"deterministic_time":1529.1573791504,"dettime":1529.1573791504,"gap":0.0,"mip_relative_gap":0.0,"nb_iterations":4807,"nb_linear_nonzeros":1259,"nb_nodes_processed":95,"problem_type":"MILP","quality_metrics":{},"status":"integer optimal solution","status_code":101,"time":1.313},"46":{"NOT_A_NUM":null,"best_bound":84.0,"columns":311,"deterministic_time":1546.6991691589,"dettime":1546.6991691589,"gap":0.0,"mip_relative_gap":0.0,"nb_iterations":5212,"nb_linear_nonzeros":1259,"nb_nodes_processed":107,"problem_type":"MILP","quality_metrics":{},"status":"integer optimal solution","status_code":101,"time":1.375},"52":{"NOT_A_NUM":null,"best_bound":84.0,"columns":311,"deterministic_time":1546.6991691589,"dettime":1546.6991691589,"gap":0.0,"mip_relative_gap":0.0,"nb_iterations":5212,"nb_linear_nonzeros":1259,"nb_nodes_processed":107,"problem_type":"MILP","quality_metrics":{},"status":"integer optimal solution","status_code":101,"time":1.328},"129":{"NOT_A_NUM":null,"best_bound":84.0,"columns":311,"deterministic_time":1546.3296289444,"dettime":1546.3296289444,"gap":0.0,"mip_relative_gap":0.0,"nb_iterations":5212,"nb_linear_nonzeros":1259,"nb_nodes_processed":107,"problem_type":"MILP","quality_metrics":{},"status":"integer optimal solution","status_code":101,"time":1.344},"126":{"NOT_A_NUM":null,"best_bound":84.0,"columns":311,"deterministic_time":1546.3296289444,"dettime":1546.3296289444,"gap":0.0,"mip_relative_gap":0.0,"nb_iterations":5212,"nb_linear_nonzeros":1259,"nb_nodes_processed":107,"problem_type":"MILP","quality_metrics":{},"status":"integer optimal solution","status_code":101,"time":1.359},"45":{"NOT_A_NUM":null,"best_bound":84.0,"columns":311,"deterministic_time":1546.3296289444,"dettime":1546.3296289444,"gap":0.0,"mip_relative_gap":0.0,"nb_iterations":5212,"nb_linear_nonzeros":1259,"nb_nodes_processed":107,"problem_type":"MILP","quality_metrics":{},"status":"integer optimal solution","status_code":101,"time":1.328},"48":{"NOT_A_NUM":null,"best_bound":84.0,"columns":311,"deterministic_time":1546.3296289444,"dettime":1546.3296289444,"gap":0.0,"mip_relative_gap":0.0,"nb_iterations":5212,"nb_linear_nonzeros":1259,"nb_nodes_processed":107,"problem_type":"MILP","quality_metrics":{},"status":"integer optimal solution","status_code":101,"time":1.329},"49":{"NOT_A_NUM":null,"best_bound":84.0,"columns":311,"deterministic_time":1546.6991691589,"dettime":1546.6991691589,"gap":0.0,"mip_relative_gap":0.0,"nb_iterations":5212,"nb_linear_nonzeros":1259,"nb_nodes_processed":107,"problem_type":"MILP","quality_metrics":{},"status":"integer optimal solution","status_code":101,"time":1.344},"51":{"NOT_A_NUM":null,"best_bound":84.0,"columns":311,"deterministic_time":1546.3296289444,"dettime":1546.3296289444,"gap":0.0,"mip_relative_gap":0.0,"nb_iterations":5212,"nb_linear_nonzeros":1259,"nb_nodes_processed":107,"problem_type":"MILP","quality_metrics":{},"status":"integer optimal solution","status_code":101,"time":1.312},"127":{"NOT_A_NUM":null,"best_bound":84.0,"columns":311,"deterministic_time":1546.6991691589,"dettime":1546.6991691589,"gap":0.0,"mip_relative_gap":0.0,"nb_iterations":5212,"nb_linear_nonzeros":1259,"nb_nodes_processed":107,"problem_type":"MILP","quality_metrics":{},"status":"integer optimal solution","status_code":101,"time":1.343},"130":{"NOT_A_NUM":null,"best_bound":84.0,"columns":311,"deterministic_time":1546.6991691589,"dettime":1546.6991691589,"gap":0.0,"mip_relative_gap":0.0,"nb_iterations":5212,"nb_linear_nonzeros":1259,"nb_nodes_processed":107,"problem_type":"MILP","quality_metrics":{},"status":"integer optimal solution","status_code":101,"time":1.328},"132":{"NOT_A_NUM":null,"best_bound":84.0,"columns":311,"deterministic_time":1546.3296289444,"dettime":1546.3296289444,"gap":0.0,"mip_relative_gap":0.0,"nb_iterations":5212,"nb_linear_nonzeros":1259,"nb_nodes_processed":107,"problem_type":"MILP","quality_metrics":{},"status":"integer optimal solution","status_code":101,"time":1.359},"133":{"NOT_A_NUM":null,"best_bound":84.0,"columns":311,"deterministic_time":1546.6991691589,"dettime":1546.6991691589,"gap":0.0,"mip_relative_gap":0.0,"nb_iterations":5212,"nb_linear_nonzeros":1259,"nb_nodes_processed":107,"problem_type":"MILP","quality_metrics":{},"status":"integer optimal solution","status_code":101,"time":1.313}},"config":{"32":{"threads":1,"mip.strategy.search":1,"lpmethod":1,"mip.cuts.gomory":1,"mip.cuts.liftproj":0,"mip.cuts.mircut":1,"mip.cuts.zerohalfcut":2},"113":{"threads":1,"mip.strategy.search":1,"lpmethod":2,"mip.cuts.gomory":1,"mip.cuts.liftproj":0,"mip.cuts.mircut":1,"mip.cuts.zerohalfcut":2},"38":{"threads":1,"mip.strategy.search":1,"lpmethod":1,"mip.cuts.gomory":1,"mip.cuts.liftproj":1,"mip.cuts.mircut":0,"mip.cuts.zerohalfcut":2},"122":{"threads":1,"mip.strategy.search":1,"lpmethod":2,"mip.cuts.gomory":1,"mip.cuts.liftproj":1,"mip.cuts.mircut":1,"mip.cuts.zerohalfcut":2},"44":{"threads":1,"mip.strategy.search":1,"lpmethod":1,"mip.cuts.gomory":1,"mip.cuts.liftproj":1,"mip.cuts.mircut":2,"mip.cuts.zerohalfcut":2},"29":{"threads":1,"mip.strategy.search":1,"lpmethod":1,"mip.cuts.gomory":1,"mip.cuts.liftproj":0,"mip.cuts.mircut":0,"mip.cuts.zerohalfcut":2},"41":{"threads":1,"mip.strategy.search":1,"lpmethod":1,"mip.cuts.gomory":1,"mip.cuts.liftproj":1,"mip.cuts.mircut":1,"mip.cuts.zerohalfcut":2},"35":{"threads":1,"mip.strategy.search":1,"lpmethod":1,"mip.cuts.gomory":1,"mip.cuts.liftproj":0,"mip.cuts.mircut":2,"mip.cuts.zerohalfcut":2},"125":{"threads":1,"mip.strategy.search":1,"lpmethod":2,"mip.cuts.gomory":1,"mip.cuts.liftproj":1,"mip.cuts.mircut":2,"mip.cuts.zerohalfcut":2},"119":{"threads":1,"mip.strategy.search":1,"lpmethod":2,"mip.cuts.gomory":1,"mip.cuts.liftproj":1,"mip.cuts.mircut":0,"mip.cuts.zerohalfcut":2},"110":{"threads":1,"mip.strategy.search":1,"lpmethod":2,"mip.cuts.gomory":1,"mip.cuts.liftproj":0,"mip.cuts.mircut":0,"mip.cuts.zerohalfcut":2},"116":{"threads":1,"mip.strategy.search":1,"lpmethod":2,"mip.cuts.gomory":1,"mip.cuts.liftproj":0,"mip.cuts.mircut":2,"mip.cuts.zerohalfcut":2},"118":{"threads":1,"mip.strategy.search":1,"lpmethod":2,"mip.cuts.gomory":1,"mip.cuts.liftproj":1,"mip.cuts.mircut":0,"mip.cuts.zerohalfcut":1},"33":{"threads":1,"mip.strategy.search":1,"lpmethod":1,"mip.cuts.gomory":1,"mip.cuts.liftproj":0,"mip.cuts.mircut":2,"mip.cuts.zerohalfcut":0},"42":{"threads":1,"mip.strategy.search":1,"lpmethod":1,"mip.cuts.gomory":1,"mip.cuts.liftproj":1,"mip.cuts.mircut":2,"mip.cuts.zerohalfcut":0},"121":{"threads":1,"mip.strategy.search":1,"lpmethod":2,"mip.cuts.gomory":1,"mip.cuts.liftproj":1,"mip.cuts.mircut":1,"mip.cuts.zerohalfcut":1},"39":{"threads":1,"mip.strategy.search":1,"lpmethod":1,"mip.cuts.gomory":1,"mip.cuts.liftproj":1,"mip.cuts.mircut":1,"mip.cuts.zerohalfcut":0},"36":{"threads":1,"mip.strategy.search":1,"lpmethod":1,"mip.cuts.gomory":1,"mip.cuts.liftproj":1,"mip.cuts.mircut":0,"mip.cuts.zerohalfcut":0},"37":{"threads":1,"mip.strategy.search":1,"lpmethod":1,"mip.cuts.gomory":1,"mip.cuts.liftproj":1,"mip.cuts.mircut":0,"mip.cuts.zerohalfcut":1},"27":{"threads":1,"mip.strategy.search":1,"lpmethod":1,"mip.cuts.gomory":1,"mip.cuts.liftproj":0,"mip.cuts.mircut":0,"mip.cuts.zerohalfcut":0},"115":{"threads":1,"mip.strategy.search":1,"lpmethod":2,"mip.cuts.gomory":1,"mip.cuts.liftproj":0,"mip.cuts.mircut":2,"mip.cuts.zerohalfcut":1},"112":{"threads":1,"mip.strategy.search":1,"lpmethod":2,"mip.cuts.gomory":1,"mip.cuts.liftproj":0,"mip.cuts.mircut":1,"mip.cuts.zerohalfcut":1},"111":{"threads":1,"mip.strategy.search":1,"lpmethod":2,"mip.cuts.gomory":1,"mip.cuts.liftproj":0,"mip.cuts.mircut":1,"mip.cuts.zerohalfcut":0},"28":{"threads":1,"mip.strategy.search":1,"lpmethod":1,"mip.cuts.gomory":1,"mip.cuts.liftproj":0,"mip.cuts.mircut":0,"mip.cuts.zerohalfcut":1},"34":{"threads":1,"mip.strategy.search":1,"lpmethod":1,"mip.cuts.gomory":1,"mip.cuts.liftproj":0,"mip.cuts.mircut":2,"mip.cuts.zerohalfcut":1},"40":{"threads":1,"mip.strategy.search":1,"lpmethod":1,"mip.cuts.gomory":1,"mip.cuts.liftproj":1,"mip.cuts.mircut":1,"mip.cuts.zerohalfcut":1},"124":{"threads":1,"mip.strategy.search":1,"lpmethod":2,"mip.cuts.gomory":1,"mip.cuts.liftproj":1,"mip.cuts.mircut":2,"mip.cuts.zerohalfcut":1},"123":{"threads":1,"mip.strategy.search":1,"lpmethod":2,"mip.cuts.gomory":1,"mip.cuts.liftproj":1,"mip.cuts.mircut":2,"mip.cuts.zerohalfcut":0},"120":{"threads":1,"mip.strategy.search":1,"lpmethod":2,"mip.cuts.gomory":1,"mip.cuts.liftproj":1,"mip.cuts.mircut":1,"mip.cuts.zerohalfcut":0},"30":{"threads":1,"mip.strategy.search":1,"lpmethod":1,"mip.cuts.gomory":1,"mip.cuts.liftproj":0,"mip.cuts.mircut":1,"mip.cuts.zerohalfcut":0},"114":{"threads":1,"mip.strategy.search":1,"lpmethod":2,"mip.cuts.gomory":1,"mip.cuts.liftproj":0,"mip.cuts.mircut":2,"mip.cuts.zerohalfcut":0},"109":{"threads":1,"mip.strategy.search":1,"lpmethod":2,"mip.cuts.gomory":1,"mip.cuts.liftproj":0,"mip.cuts.mircut":0,"mip.cuts.zerohalfcut":1},"43":{"threads":1,"mip.strategy.search":1,"lpmethod":1,"mip.cuts.gomory":1,"mip.cuts.liftproj":1,"mip.cuts.mircut":2,"mip.cuts.zerohalfcut":1},"31":{"threads":1,"mip.strategy.search":1,"lpmethod":1,"mip.cuts.gomory":1,"mip.cuts.liftproj":0,"mip.cuts.mircut":1,"mip.cuts.zerohalfcut":1},"117":{"threads":1,"mip.strategy.search":1,"lpmethod":2,"mip.cuts.gomory":1,"mip.cuts.liftproj":1,"mip.cuts.mircut":0,"mip.cuts.zerohalfcut":0},"108":{"threads":1,"mip.strategy.search":1,"lpmethod":2,"mip.cuts.gomory":1,"mip.cuts.liftproj":0,"mip.cuts.mircut":0,"mip.cuts.zerohalfcut":0},"91":{"threads":1,"mip.strategy.search":1,"lpmethod":2,"mip.cuts.gomory":0,"mip.cuts.liftproj":1,"mip.cuts.mircut":0,"mip.cuts.zerohalfcut":1},"13":{"threads":1,"mip.strategy.search":1,"lpmethod":1,"mip.cuts.gomory":0,"mip.cuts.liftproj":1,"mip.cuts.mircut":1,"mip.cuts.zerohalfcut":1},"88":{"threads":1,"mip.strategy.search":1,"lpmethod":2,"mip.cuts.gomory":0,"mip.cuts.liftproj":0,"mip.cuts.mircut":2,"mip.cuts.zerohalfcut":1},"82":{"threads":1,"mip.strategy.search":1,"lpmethod":2,"mip.cuts.gomory":0,"mip.cuts.liftproj":0,"mip.cuts.mircut":0,"mip.cuts.zerohalfcut":1},"84":{"threads":1,"mip.strategy.search":1,"lpmethod":2,"mip.cuts.gomory":0,"mip.cuts.liftproj":0,"mip.cuts.mircut":1,"mip.cuts.zerohalfcut":0},"97":{"threads":1,"mip.strategy.search":1,"lpmethod":2,"mip.cuts.gomory":0,"mip.cuts.liftproj":1,"mip.cuts.mircut":2,"mip.cuts.zerohalfcut":1},"93":{"threads":1,"mip.strategy.search":1,"lpmethod":2,"mip.cuts.gomory":0,"mip.cuts.liftproj":1,"mip.cuts.mircut":1,"mip.cuts.zerohalfcut":0},"12":{"threads":1,"mip.strategy.search":1,"lpmethod":1,"mip.cuts.gomory":0,"mip.cuts.liftproj":1,"mip.cuts.mircut":1,"mip.cuts.zerohalfcut":0},"81":{"threads":1,"mip.strategy.search":1,"lpmethod":2,"mip.cuts.gomory":0,"mip.cuts.liftproj":0,"mip.cuts.mircut":0,"mip.cuts.zerohalfcut":0},"85":{"threads":1,"mip.strategy.search":1,"lpmethod":2,"mip.cuts.gomory":0,"mip.cuts.liftproj":0,"mip.cuts.mircut":1,"mip.cuts.zerohalfcut":1},"10":{"threads":1,"mip.strategy.search":1,"lpmethod":1,"mip.cuts.gomory":0,"mip.cuts.liftproj":1,"mip.cuts.mircut":0,"mip.cuts.zerohalfcut":1},"16":{"threads":1,"mip.strategy.search":1,"lpmethod":1,"mip.cuts.gomory":0,"mip.cuts.liftproj":1,"mip.cuts.mircut":2,"mip.cuts.zerohalfcut":1},"96":{"threads":1,"mip.strategy.search":1,"lpmethod":2,"mip.cuts.gomory":0,"mip.cuts.liftproj":1,"mip.cuts.mircut":2,"mip.cuts.zerohalfcut":0},"94":{"threads":1,"mip.strategy.search":1,"lpmethod":2,"mip.cuts.gomory":0,"mip.cuts.liftproj":1,"mip.cuts.mircut":1,"mip.cuts.zerohalfcut":1},"90":{"threads":1,"mip.strategy.search":1,"lpmethod":2,"mip.cuts.gomory":0,"mip.cuts.liftproj":1,"mip.cuts.mircut":0,"mip.cuts.zerohalfcut":0},"15":{"threads":1,"mip.strategy.search":1,"lpmethod":1,"mip.cuts.gomory":0,"mip.cuts.liftproj":1,"mip.cuts.mircut":2,"mip.cuts.zerohalfcut":0},"7":{"threads":1,"mip.strategy.search":1,"lpmethod":1,"mip.cuts.gomory":0,"mip.cuts.liftproj":0,"mip.cuts.mircut":2,"mip.cuts.zerohalfcut":1},"87":{"threads":1,"mip.strategy.search":1,"lpmethod":2,"mip.cuts.gomory":0,"mip.cuts.liftproj":0,"mip.cuts.mircut":2,"mip.cuts.zerohalfcut":0},"9":{"threads":1,"mip.strategy.search":1,"lpmethod":1,"mip.cuts.gomory":0,"mip.cuts.liftproj":1,"mip.cuts.mircut":0,"mip.cuts.zerohalfcut":0},"4":{"threads":1,"mip.strategy.search":1,"lpmethod":1,"mip.cuts.gomory":0,"mip.cuts.liftproj":0,"mip.cuts.mircut":1,"mip.cuts.zerohalfcut":1},"6":{"threads":1,"mip.strategy.search":1,"lpmethod":1,"mip.cuts.gomory":0,"mip.cuts.liftproj":0,"mip.cuts.mircut":2,"mip.cuts.zerohalfcut":0},"1":{"threads":1,"mip.strategy.search":1,"lpmethod":1,"mip.cuts.gomory":0,"mip.cuts.liftproj":0,"mip.cuts.mircut":0,"mip.cuts.zerohalfcut":1},"3":{"threads":1,"mip.strategy.search":1,"lpmethod":1,"mip.cuts.gomory":0,"mip.cuts.liftproj":0,"mip.cuts.mircut":1,"mip.cuts.zerohalfcut":0},"86":{"threads":1,"mip.strategy.search":1,"lpmethod":2,"mip.cuts.gomory":0,"mip.cuts.liftproj":0,"mip.cuts.mircut":1,"mip.cuts.zerohalfcut":2},"2":{"threads":1,"mip.strategy.search":1,"lpmethod":1,"mip.cuts.gomory":0,"mip.cuts.liftproj":0,"mip.cuts.mircut":0,"mip.cuts.zerohalfcut":2},"98":{"threads":1,"mip.strategy.search":1,"lpmethod":2,"mip.cuts.gomory":0,"mip.cuts.liftproj":1,"mip.cuts.mircut":2,"mip.cuts.zerohalfcut":2},"5":{"threads":1,"mip.strategy.search":1,"lpmethod":1,"mip.cuts.gomory":0,"mip.cuts.liftproj":0,"mip.cuts.mircut":1,"mip.cuts.zerohalfcut":2},"17":{"threads":1,"mip.strategy.search":1,"lpmethod":1,"mip.cuts.gomory":0,"mip.cuts.liftproj":1,"mip.cuts.mircut":2,"mip.cuts.zerohalfcut":2},"83":{"threads":1,"mip.strategy.search":1,"lpmethod":2,"mip.cuts.gomory":0,"mip.cuts.liftproj":0,"mip.cuts.mircut":0,"mip.cuts.zerohalfcut":2},"89":{"threads":1,"mip.strategy.search":1,"lpmethod":2,"mip.cuts.gomory":0,"mip.cuts.liftproj":0,"mip.cuts.mircut":2,"mip.cuts.zerohalfcut":2},"95":{"threads":1,"mip.strategy.search":1,"lpmethod":2,"mip.cuts.gomory":0,"mip.cuts.liftproj":1,"mip.cuts.mircut":1,"mip.cuts.zerohalfcut":2},"92":{"threads":1,"mip.strategy.search":1,"lpmethod":2,"mip.cuts.gomory":0,"mip.cuts.liftproj":1,"mip.cuts.mircut":0,"mip.cuts.zerohalfcut":2},"14":{"threads":1,"mip.strategy.search":1,"lpmethod":1,"mip.cuts.gomory":0,"mip.cuts.liftproj":1,"mip.cuts.mircut":1,"mip.cuts.zerohalfcut":2},"11":{"threads":1,"mip.strategy.search":1,"lpmethod":1,"mip.cuts.gomory":0,"mip.cuts.liftproj":1,"mip.cuts.mircut":0,"mip.cuts.zerohalfcut":2},"8":{"threads":1,"mip.strategy.search":1,"lpmethod":1,"mip.cuts.gomory":0,"mip.cuts.liftproj":0,"mip.cuts.mircut":2,"mip.cuts.zerohalfcut":2},"0":{"threads":1,"mip.strategy.search":1,"lpmethod":1,"mip.cuts.gomory":0,"mip.cuts.liftproj":0,"mip.cuts.mircut":0,"mip.cuts.zerohalfcut":0},"71":{"threads":1,"mip.strategy.search":1,"lpmethod":1,"mip.cuts.gomory":2,"mip.cuts.liftproj":1,"mip.cuts.mircut":2,"mip.cuts.zerohalfcut":2},"137":{"threads":1,"mip.strategy.search":1,"lpmethod":2,"mip.cuts.gomory":2,"mip.cuts.liftproj":0,"mip.cuts.mircut":0,"mip.cuts.zerohalfcut":2},"152":{"threads":1,"mip.strategy.search":1,"lpmethod":2,"mip.cuts.gomory":2,"mip.cuts.liftproj":1,"mip.cuts.mircut":2,"mip.cuts.zerohalfcut":2},"65":{"threads":1,"mip.strategy.search":1,"lpmethod":1,"mip.cuts.gomory":2,"mip.cuts.liftproj":1,"mip.cuts.mircut":0,"mip.cuts.zerohalfcut":2},"68":{"threads":1,"mip.strategy.search":1,"lpmethod":1,"mip.cuts.gomory":2,"mip.cuts.liftproj":1,"mip.cuts.mircut":1,"mip.cuts.zerohalfcut":2},"59":{"threads":1,"mip.strategy.search":1,"lpmethod":1,"mip.cuts.gomory":2,"mip.cuts.liftproj":0,"mip.cuts.mircut":1,"mip.cuts.zerohalfcut":2},"140":{"threads":1,"mip.strategy.search":1,"lpmethod":2,"mip.cuts.gomory":2,"mip.cuts.liftproj":0,"mip.cuts.mircut":1,"mip.cuts.zerohalfcut":2},"149":{"threads":1,"mip.strategy.search":1,"lpmethod":2,"mip.cuts.gomory":2,"mip.cuts.liftproj":1,"mip.cuts.mircut":1,"mip.cuts.zerohalfcut":2},"146":{"threads":1,"mip.strategy.search":1,"lpmethod":2,"mip.cuts.gomory":2,"mip.cuts.liftproj":1,"mip.cuts.mircut":0,"mip.cuts.zerohalfcut":2},"56":{"threads":1,"mip.strategy.search":1,"lpmethod":1,"mip.cuts.gomory":2,"mip.cuts.liftproj":0,"mip.cuts.mircut":0,"mip.cuts.zerohalfcut":2},"143":{"threads":1,"mip.strategy.search":1,"lpmethod":2,"mip.cuts.gomory":2,"mip.cuts.liftproj":0,"mip.cuts.mircut":2,"mip.cuts.zerohalfcut":2},"62":{"threads":1,"mip.strategy.search":1,"lpmethod":1,"mip.cuts.gomory":2,"mip.cuts.liftproj":0,"mip.cuts.mircut":2,"mip.cuts.zerohalfcut":2},"63":{"threads":1,"mip.strategy.search":1,"lpmethod":1,"mip.cuts.gomory":2,"mip.cuts.liftproj":1,"mip.cuts.mircut":0,"mip.cuts.zerohalfcut":0},"135":{"threads":1,"mip.strategy.search":1,"lpmethod":2,"mip.cuts.gomory":2,"mip.cuts.liftproj":0,"mip.cuts.mircut":0,"mip.cuts.zerohalfcut":0},"58":{"threads":1,"mip.strategy.search":1,"lpmethod":1,"mip.cuts.gomory":2,"mip.cuts.liftproj":0,"mip.cuts.mircut":1,"mip.cuts.zerohalfcut":1},"148":{"threads":1,"mip.strategy.search":1,"lpmethod":2,"mip.cuts.gomory":2,"mip.cuts.liftproj":1,"mip.cuts.mircut":1,"mip.cuts.zerohalfcut":1},"138":{"threads":1,"mip.strategy.search":1,"lpmethod":2,"mip.cuts.gomory":2,"mip.cuts.liftproj":0,"mip.cuts.mircut":1,"mip.cuts.zerohalfcut":0},"151":{"threads":1,"mip.strategy.search":1,"lpmethod":2,"mip.cuts.gomory":2,"mip.cuts.liftproj":1,"mip.cuts.mircut":2,"mip.cuts.zerohalfcut":1},"64":{"threads":1,"mip.strategy.search":1,"lpmethod":1,"mip.cuts.gomory":2,"mip.cuts.liftproj":1,"mip.cuts.mircut":0,"mip.cuts.zerohalfcut":1},"141":{"threads":1,"mip.strategy.search":1,"lpmethod":2,"mip.cuts.gomory":2,"mip.cuts.liftproj":0,"mip.cuts.mircut":2,"mip.cuts.zerohalfcut":0},"139":{"threads":1,"mip.strategy.search":1,"lpmethod":2,"mip.cuts.gomory":2,"mip.cuts.liftproj":0,"mip.cuts.mircut":1,"mip.cuts.zerohalfcut":1},"54":{"threads":1,"mip.strategy.search":1,"lpmethod":1,"mip.cuts.gomory":2,"mip.cuts.liftproj":0,"mip.cuts.mircut":0,"mip.cuts.zerohalfcut":0},"57":{"threads":1,"mip.strategy.search":1,"lpmethod":1,"mip.cuts.gomory":2,"mip.cuts.liftproj":0,"mip.cuts.mircut":1,"mip.cuts.zerohalfcut":0},"147":{"threads":1,"mip.strategy.search":1,"lpmethod":2,"mip.cuts.gomory":2,"mip.cuts.liftproj":1,"mip.cuts.mircut":1,"mip.cuts.zerohalfcut":0},"69":{"threads":1,"mip.strategy.search":1,"lpmethod":1,"mip.cuts.gomory":2,"mip.cuts.liftproj":1,"mip.cuts.mircut":2,"mip.cuts.zerohalfcut":0},"66":{"threads":1,"mip.strategy.search":1,"lpmethod":1,"mip.cuts.gomory":2,"mip.cuts.liftproj":1,"mip.cuts.mircut":1,"mip.cuts.zerohalfcut":0},"61":{"threads":1,"mip.strategy.search":1,"lpmethod":1,"mip.cuts.gomory":2,"mip.cuts.liftproj":0,"mip.cuts.mircut":2,"mip.cuts.zerohalfcut":1},"144":{"threads":1,"mip.strategy.search":1,"lpmethod":2,"mip.cuts.gomory":2,"mip.cuts.liftproj":1,"mip.cuts.mircut":0,"mip.cuts.zerohalfcut":0},"145":{"threads":1,"mip.strategy.search":1,"lpmethod":2,"mip.cuts.gomory":2,"mip.cuts.liftproj":1,"mip.cuts.mircut":0,"mip.cuts.zerohalfcut":1},"136":{"threads":1,"mip.strategy.search":1,"lpmethod":2,"mip.cuts.gomory":2,"mip.cuts.liftproj":0,"mip.cuts.mircut":0,"mip.cuts.zerohalfcut":1},"67":{"threads":1,"mip.strategy.search":1,"lpmethod":1,"mip.cuts.gomory":2,"mip.cuts.liftproj":1,"mip.cuts.mircut":1,"mip.cuts.zerohalfcut":1},"142":{"threads":1,"mip.strategy.search":1,"lpmethod":2,"mip.cuts.gomory":2,"mip.cuts.liftproj":0,"mip.cuts.mircut":2,"mip.cuts.zerohalfcut":1},"150":{"threads":1,"mip.strategy.search":1,"lpmethod":2,"mip.cuts.gomory":2,"mip.cuts.liftproj":1,"mip.cuts.mircut":2,"mip.cuts.zerohalfcut":0},"60":{"threads":1,"mip.strategy.search":1,"lpmethod":1,"mip.cuts.gomory":2,"mip.cuts.liftproj":0,"mip.cuts.mircut":2,"mip.cuts.zerohalfcut":0},"70":{"threads":1,"mip.strategy.search":1,"lpmethod":1,"mip.cuts.gomory":2,"mip.cuts.liftproj":1,"mip.cuts.mircut":2,"mip.cuts.zerohalfcut":1},"55":{"threads":1,"mip.strategy.search":1,"lpmethod":1,"mip.cuts.gomory":2,"mip.cuts.liftproj":0,"mip.cuts.mircut":0,"mip.cuts.zerohalfcut":1},"77":{"threads":1,"mip.strategy.search":1,"lpmethod":1,"mip.cuts.gomory":2,"mip.cuts.liftproj":2,"mip.cuts.mircut":1,"mip.cuts.zerohalfcut":2},"80":{"threads":1,"mip.strategy.search":1,"lpmethod":1,"mip.cuts.gomory":2,"mip.cuts.liftproj":2,"mip.cuts.mircut":2,"mip.cuts.zerohalfcut":2},"158":{"threads":1,"mip.strategy.search":1,"lpmethod":2,"mip.cuts.gomory":2,"mip.cuts.liftproj":2,"mip.cuts.mircut":1,"mip.cuts.zerohalfcut":2},"74":{"threads":1,"mip.strategy.search":1,"lpmethod":1,"mip.cuts.gomory":2,"mip.cuts.liftproj":2,"mip.cuts.mircut":0,"mip.cuts.zerohalfcut":2},"73":{"threads":1,"mip.strategy.search":1,"lpmethod":1,"mip.cuts.gomory":2,"mip.cuts.liftproj":2,"mip.cuts.mircut":0,"mip.cuts.zerohalfcut":1},"154":{"threads":1,"mip.strategy.search":1,"lpmethod":2,"mip.cuts.gomory":2,"mip.cuts.liftproj":2,"mip.cuts.mircut":0,"mip.cuts.zerohalfcut":1},"76":{"threads":1,"mip.strategy.search":1,"lpmethod":1,"mip.cuts.gomory":2,"mip.cuts.liftproj":2,"mip.cuts.mircut":1,"mip.cuts.zerohalfcut":1},"79":{"threads":1,"mip.strategy.search":1,"lpmethod":1,"mip.cuts.gomory":2,"mip.cuts.liftproj":2,"mip.cuts.mircut":2,"mip.cuts.zerohalfcut":1},"161":{"threads":1,"mip.strategy.search":1,"lpmethod":2,"mip.cuts.gomory":2,"mip.cuts.liftproj":2,"mip.cuts.mircut":2,"mip.cuts.zerohalfcut":2},"155":{"threads":1,"mip.strategy.search":1,"lpmethod":2,"mip.cuts.gomory":2,"mip.cuts.liftproj":2,"mip.cuts.mircut":0,"mip.cuts.zerohalfcut":2},"157":{"threads":1,"mip.strategy.search":1,"lpmethod":2,"mip.cuts.gomory":2,"mip.cuts.liftproj":2,"mip.cuts.mircut":1,"mip.cuts.zerohalfcut":1},"160":{"threads":1,"mip.strategy.search":1,"lpmethod":2,"mip.cuts.gomory":2,"mip.cuts.liftproj":2,"mip.cuts.mircut":2,"mip.cuts.zerohalfcut":1},"99":{"threads":1,"mip.strategy.search":1,"lpmethod":2,"mip.cuts.gomory":0,"mip.cuts.liftproj":2,"mip.cuts.mircut":0,"mip.cuts.zerohalfcut":0},"102":{"threads":1,"mip.strategy.search":1,"lpmethod":2,"mip.cuts.gomory":0,"mip.cuts.liftproj":2,"mip.cuts.mircut":1,"mip.cuts.zerohalfcut":0},"18":{"threads":1,"mip.strategy.search":1,"lpmethod":1,"mip.cuts.gomory":0,"mip.cuts.liftproj":2,"mip.cuts.mircut":0,"mip.cuts.zerohalfcut":0},"24":{"threads":1,"mip.strategy.search":1,"lpmethod":1,"mip.cuts.gomory":0,"mip.cuts.liftproj":2,"mip.cuts.mircut":2,"mip.cuts.zerohalfcut":0},"105":{"threads":1,"mip.strategy.search":1,"lpmethod":2,"mip.cuts.gomory":0,"mip.cuts.liftproj":2,"mip.cuts.mircut":2,"mip.cuts.zerohalfcut":0},"21":{"threads":1,"mip.strategy.search":1,"lpmethod":1,"mip.cuts.gomory":0,"mip.cuts.liftproj":2,"mip.cuts.mircut":1,"mip.cuts.zerohalfcut":0},"72":{"threads":1,"mip.strategy.search":1,"lpmethod":1,"mip.cuts.gomory":2,"mip.cuts.liftproj":2,"mip.cuts.mircut":0,"mip.cuts.zerohalfcut":0},"159":{"threads":1,"mip.strategy.search":1,"lpmethod":2,"mip.cuts.gomory":2,"mip.cuts.liftproj":2,"mip.cuts.mircut":2,"mip.cuts.zerohalfcut":0},"153":{"threads":1,"mip.strategy.search":1,"lpmethod":2,"mip.cuts.gomory":2,"mip.cuts.liftproj":2,"mip.cuts.mircut":0,"mip.cuts.zerohalfcut":0},"156":{"threads":1,"mip.strategy.search":1,"lpmethod":2,"mip.cuts.gomory":2,"mip.cuts.liftproj":2,"mip.cuts.mircut":1,"mip.cuts.zerohalfcut":0},"75":{"threads":1,"mip.strategy.search":1,"lpmethod":1,"mip.cuts.gomory":2,"mip.cuts.liftproj":2,"mip.cuts.mircut":1,"mip.cuts.zerohalfcut":0},"78":{"threads":1,"mip.strategy.search":1,"lpmethod":1,"mip.cuts.gomory":2,"mip.cuts.liftproj":2,"mip.cuts.mircut":2,"mip.cuts.zerohalfcut":0},"104":{"threads":1,"mip.strategy.search":1,"lpmethod":2,"mip.cuts.gomory":0,"mip.cuts.liftproj":2,"mip.cuts.mircut":1,"mip.cuts.zerohalfcut":2},"26":{"threads":1,"mip.strategy.search":1,"lpmethod":1,"mip.cuts.gomory":0,"mip.cuts.liftproj":2,"mip.cuts.mircut":2,"mip.cuts.zerohalfcut":2},"20":{"threads":1,"mip.strategy.search":1,"lpmethod":1,"mip.cuts.gomory":0,"mip.cuts.liftproj":2,"mip.cuts.mircut":0,"mip.cuts.zerohalfcut":2},"101":{"threads":1,"mip.strategy.search":1,"lpmethod":2,"mip.cuts.gomory":0,"mip.cuts.liftproj":2,"mip.cuts.mircut":0,"mip.cuts.zerohalfcut":2},"107":{"threads":1,"mip.strategy.search":1,"lpmethod":2,"mip.cuts.gomory":0,"mip.cuts.liftproj":2,"mip.cuts.mircut":2,"mip.cuts.zerohalfcut":2},"23":{"threads":1,"mip.strategy.search":1,"lpmethod":1,"mip.cuts.gomory":0,"mip.cuts.liftproj":2,"mip.cuts.mircut":1,"mip.cuts.zerohalfcut":2},"19":{"threads":1,"mip.strategy.search":1,"lpmethod":1,"mip.cuts.gomory":0,"mip.cuts.liftproj":2,"mip.cuts.mircut":0,"mip.cuts.zerohalfcut":1},"22":{"threads":1,"mip.strategy.search":1,"lpmethod":1,"mip.cuts.gomory":0,"mip.cuts.liftproj":2,"mip.cuts.mircut":1,"mip.cuts.zerohalfcut":1},"103":{"threads":1,"mip.strategy.search":1,"lpmethod":2,"mip.cuts.gomory":0,"mip.cuts.liftproj":2,"mip.cuts.mircut":1,"mip.cuts.zerohalfcut":1},"100":{"threads":1,"mip.strategy.search":1,"lpmethod":2,"mip.cuts.gomory":0,"mip.cuts.liftproj":2,"mip.cuts.mircut":0,"mip.cuts.zerohalfcut":1},"106":{"threads":1,"mip.strategy.search":1,"lpmethod":2,"mip.cuts.gomory":0,"mip.cuts.liftproj":2,"mip.cuts.mircut":2,"mip.cuts.zerohalfcut":1},"25":{"threads":1,"mip.strategy.search":1,"lpmethod":1,"mip.cuts.gomory":0,"mip.cuts.liftproj":2,"mip.cuts.mircut":2,"mip.cuts.zerohalfcut":1},"134":{"threads":1,"mip.strategy.search":1,"lpmethod":2,"mip.cuts.gomory":1,"mip.cuts.liftproj":2,"mip.cuts.mircut":2,"mip.cuts.zerohalfcut":2},"53":{"threads":1,"mip.strategy.search":1,"lpmethod":1,"mip.cuts.gomory":1,"mip.cuts.liftproj":2,"mip.cuts.mircut":2,"mip.cuts.zerohalfcut":2},"131":{"threads":1,"mip.strategy.search":1,"lpmethod":2,"mip.cuts.gomory":1,"mip.cuts.liftproj":2,"mip.cuts.mircut":1,"mip.cuts.zerohalfcut":2},"47":{"threads":1,"mip.strategy.search":1,"lpmethod":1,"mip.cuts.gomory":1,"mip.cuts.liftproj":2,"mip.cuts.mircut":0,"mip.cuts.zerohalfcut":2},"50":{"threads":1,"mip.strategy.search":1,"lpmethod":1,"mip.cuts.gomory":1,"mip.cuts.liftproj":2,"mip.cuts.mircut":1,"mip.cuts.zerohalfcut":2},"128":{"threads":1,"mip.strategy.search":1,"lpmethod":2,"mip.cuts.gomory":1,"mip.cuts.liftproj":2,"mip.cuts.mircut":0,"mip.cuts.zerohalfcut":2},"46":{"threads":1,"mip.strategy.search":1,"lpmethod":1,"mip.cuts.gomory":1,"mip.cuts.liftproj":2,"mip.cuts.mircut":0,"mip.cuts.zerohalfcut":1},"52":{"threads":1,"mip.strategy.search":1,"lpmethod":1,"mip.cuts.gomory":1,"mip.cuts.liftproj":2,"mip.cuts.mircut":2,"mip.cuts.zerohalfcut":1},"129":{"threads":1,"mip.strategy.search":1,"lpmethod":2,"mip.cuts.gomory":1,"mip.cuts.liftproj":2,"mip.cuts.mircut":1,"mip.cuts.zerohalfcut":0},"126":{"threads":1,"mip.strategy.search":1,"lpmethod":2,"mip.cuts.gomory":1,"mip.cuts.liftproj":2,"mip.cuts.mircut":0,"mip.cuts.zerohalfcut":0},"45":{"threads":1,"mip.strategy.search":1,"lpmethod":1,"mip.cuts.gomory":1,"mip.cuts.liftproj":2,"mip.cuts.mircut":0,"mip.cuts.zerohalfcut":0},"48":{"threads":1,"mip.strategy.search":1,"lpmethod":1,"mip.cuts.gomory":1,"mip.cuts.liftproj":2,"mip.cuts.mircut":1,"mip.cuts.zerohalfcut":0},"49":{"threads":1,"mip.strategy.search":1,"lpmethod":1,"mip.cuts.gomory":1,"mip.cuts.liftproj":2,"mip.cuts.mircut":1,"mip.cuts.zerohalfcut":1},"51":{"threads":1,"mip.strategy.search":1,"lpmethod":1,"mip.cuts.gomory":1,"mip.cuts.liftproj":2,"mip.cuts.mircut":2,"mip.cuts.zerohalfcut":0},"127":{"threads":1,"mip.strategy.search":1,"lpmethod":2,"mip.cuts.gomory":1,"mip.cuts.liftproj":2,"mip.cuts.mircut":0,"mip.cuts.zerohalfcut":1},"130":{"threads":1,"mip.strategy.search":1,"lpmethod":2,"mip.cuts.gomory":1,"mip.cuts.liftproj":2,"mip.cuts.mircut":1,"mip.cuts.zerohalfcut":1},"132":{"threads":1,"mip.strategy.search":1,"lpmethod":2,"mip.cuts.gomory":1,"mip.cuts.liftproj":2,"mip.cuts.mircut":2,"mip.cuts.zerohalfcut":0},"133":{"threads":1,"mip.strategy.search":1,"lpmethod":2,"mip.cuts.gomory":1,"mip.cuts.liftproj":2,"mip.cuts.mircut":2,"mip.cuts.zerohalfcut":1}},"objective":{"32":84.0,"113":84.0,"38":84.0,"122":84.0,"44":84.0,"29":84.0,"41":84.0,"35":84.0,"125":84.0,"119":84.0,"110":84.0,"116":84.0,"118":84.0,"33":84.0,"42":84.0,"121":84.0,"39":84.0,"36":84.0,"37":84.0,"27":84.0,"115":84.0,"112":84.0,"111":84.0,"28":84.0,"34":84.0,"40":84.0,"124":84.0,"123":84.0,"120":84.0,"30":84.0,"114":84.0,"109":84.0,"43":84.0,"31":84.0,"117":84.0,"108":84.0,"91":84.0,"13":84.0,"88":84.0,"82":84.0,"84":84.0,"97":84.0,"93":84.0,"12":84.0,"81":84.0,"85":84.0,"10":84.0,"16":84.0,"96":84.0,"94":84.0,"90":84.0,"15":84.0,"7":84.0,"87":84.0,"9":84.0,"4":84.0,"6":84.0,"1":84.0,"3":84.0,"86":84.0,"2":84.0,"98":84.0,"5":84.0,"17":84.0,"83":84.0,"89":84.0,"95":84.0,"92":84.0,"14":84.0,"11":84.0,"8":84.0,"0":84.0,"71":84.0,"137":84.0,"152":84.0,"65":84.0,"68":84.0,"59":84.0,"140":84.0,"149":84.0,"146":84.0,"56":84.0,"143":84.0,"62":84.0,"63":84.0,"135":84.0,"58":84.0,"148":84.0,"138":84.0,"151":84.0,"64":84.0,"141":84.0,"139":84.0,"54":84.0,"57":84.0,"147":84.0,"69":84.0,"66":84.0,"61":84.0,"144":84.0,"145":84.0,"136":84.0,"67":84.0,"142":84.0,"150":84.0,"60":84.0,"70":84.0,"55":84.0,"77":84.0,"80":84.0,"158":84.0,"74":84.0,"73":84.0,"154":84.0,"76":84.0,"79":84.0,"161":84.0,"155":84.0,"157":84.0,"160":84.0,"99":84.0,"102":84.0,"18":84.0,"24":84.0,"105":84.0,"21":84.0,"72":84.0,"159":84.0,"153":84.0,"156":84.0,"75":84.0,"78":84.0,"104":84.0,"26":84.0,"20":84.0,"101":84.0,"107":84.0,"23":84.0,"19":84.0,"22":84.0,"103":84.0,"100":84.0,"106":84.0,"25":84.0,"134":84.0,"53":84.0,"131":84.0,"47":84.0,"50":84.0,"128":84.0,"46":84.0,"52":84.0,"129":84.0,"126":84.0,"45":84.0,"48":84.0,"49":84.0,"51":84.0,"127":84.0,"130":84.0,"132":84.0,"133":84.0},"solve_status":{"32":"integer optimal solution","113":"integer optimal solution","38":"integer optimal solution","122":"integer optimal solution","44":"integer optimal solution","29":"integer optimal solution","41":"integer optimal solution","35":"integer optimal solution","125":"integer optimal solution","119":"integer optimal solution","110":"integer optimal solution","116":"integer optimal solution","118":"integer optimal solution","33":"integer optimal solution","42":"integer optimal solution","121":"integer optimal solution","39":"integer optimal solution","36":"integer optimal solution","37":"integer optimal solution","27":"integer optimal solution","115":"integer optimal solution","112":"integer optimal solution","111":"integer optimal solution","28":"integer optimal solution","34":"integer optimal solution","40":"integer optimal solution","124":"integer optimal solution","123":"integer optimal solution","120":"integer optimal solution","30":"integer optimal solution","114":"integer optimal solution","109":"integer optimal solution","43":"integer optimal solution","31":"integer optimal solution","117":"integer optimal solution","108":"integer optimal solution","91":"integer optimal solution","13":"integer optimal solution","88":"integer optimal solution","82":"integer optimal solution","84":"integer optimal solution","97":"integer optimal solution","93":"integer optimal solution","12":"integer optimal solution","81":"integer optimal solution","85":"integer optimal solution","10":"integer optimal solution","16":"integer optimal solution","96":"integer optimal solution","94":"integer optimal solution","90":"integer optimal solution","15":"integer optimal solution","7":"integer optimal solution","87":"integer optimal solution","9":"integer optimal solution","4":"integer optimal solution","6":"integer optimal solution","1":"integer optimal solution","3":"integer optimal solution","86":"integer optimal solution","2":"integer optimal solution","98":"integer optimal solution","5":"integer optimal solution","17":"integer optimal solution","83":"integer optimal solution","89":"integer optimal solution","95":"integer optimal solution","92":"integer optimal solution","14":"integer optimal solution","11":"integer optimal solution","8":"integer optimal solution","0":"integer optimal solution","71":"integer optimal solution","137":"integer optimal solution","152":"integer optimal solution","65":"integer optimal solution","68":"integer optimal solution","59":"integer optimal solution","140":"integer optimal solution","149":"integer optimal solution","146":"integer optimal solution","56":"integer optimal solution","143":"integer optimal solution","62":"integer optimal solution","63":"integer optimal solution","135":"integer optimal solution","58":"integer optimal solution","148":"integer optimal solution","138":"integer optimal solution","151":"integer optimal solution","64":"integer optimal solution","141":"integer optimal solution","139":"integer optimal solution","54":"integer optimal solution","57":"integer optimal solution","147":"integer optimal solution","69":"integer optimal solution","66":"integer optimal solution","61":"integer optimal solution","144":"integer optimal solution","145":"integer optimal solution","136":"integer optimal solution","67":"integer optimal solution","142":"integer optimal solution","150":"integer optimal solution","60":"integer optimal solution","70":"integer optimal solution","55":"integer optimal solution","77":"integer optimal solution","80":"integer optimal solution","158":"integer optimal solution","74":"integer optimal solution","73":"integer optimal solution","154":"integer optimal solution","76":"integer optimal solution","79":"integer optimal solution","161":"integer optimal solution","155":"integer optimal solution","157":"integer optimal solution","160":"integer optimal solution","99":"integer optimal solution","102":"integer optimal solution","18":"integer optimal solution","24":"integer optimal solution","105":"integer optimal solution","21":"integer optimal solution","72":"integer optimal solution","159":"integer optimal solution","153":"integer optimal solution","156":"integer optimal solution","75":"integer optimal solution","78":"integer optimal solution","104":"integer optimal solution","26":"integer optimal solution","20":"integer optimal solution","101":"integer optimal solution","107":"integer optimal solution","23":"integer optimal solution","19":"integer optimal solution","22":"integer optimal solution","103":"integer optimal solution","100":"integer optimal solution","106":"integer optimal solution","25":"integer optimal solution","134":"integer optimal solution","53":"integer optimal solution","131":"integer optimal solution","47":"integer optimal solution","50":"integer optimal solution","128":"integer optimal solution","46":"integer optimal solution","52":"integer optimal solution","129":"integer optimal solution","126":"integer optimal solution","45":"integer optimal solution","48":"integer optimal solution","49":"integer optimal solution","51":"integer optimal solution","127":"integer optimal solution","130":"integer optimal solution","132":"integer optimal solution","133":"integer optimal solution"},"gap":{"32":0.0,"113":0.0,"38":0.0,"122":0.0,"44":0.0,"29":0.0,"41":0.0,"35":0.0,"125":0.0,"119":0.0,"110":0.0,"116":0.0,"118":0.0,"33":0.0,"42":0.0,"121":0.0,"39":0.0,"36":0.0,"37":0.0,"27":0.0,"115":0.0,"112":0.0,"111":0.0,"28":0.0,"34":0.0,"40":0.0,"124":0.0,"123":0.0,"120":0.0,"30":0.0,"114":0.0,"109":0.0,"43":0.0,"31":0.0,"117":0.0,"108":0.0,"91":0.0,"13":0.0,"88":0.0,"82":0.0,"84":0.0,"97":0.0,"93":0.0,"12":0.0,"81":0.0,"85":0.0,"10":0.0,"16":0.0,"96":0.0,"94":0.0,"90":0.0,"15":0.0,"7":0.0,"87":0.0,"9":0.0,"4":0.0,"6":0.0,"1":0.0,"3":0.0,"86":0.0,"2":0.0,"98":0.0,"5":0.0,"17":0.0,"83":0.0,"89":0.0,"95":0.0,"92":0.0,"14":0.0,"11":0.0,"8":0.0,"0":0.0,"71":0.0,"137":0.0,"152":0.0,"65":0.0,"68":0.0,"59":0.0,"140":0.0,"149":0.0,"146":0.0,"56":0.0,"143":0.0,"62":0.0,"63":0.0,"135":0.0,"58":0.0,"148":0.0,"138":0.0,"151":0.0,"64":0.0,"141":0.0,"139":0.0,"54":0.0,"57":0.0,"147":0.0,"69":0.0,"66":0.0,"61":0.0,"144":0.0,"145":0.0,"136":0.0,"67":0.0,"142":0.0,"150":0.0,"60":0.0,"70":0.0,"55":0.0,"77":0.0,"80":0.0,"158":0.0,"74":0.0,"73":0.0,"154":0.0,"76":0.0,"79":0.0,"161":0.0,"155":0.0,"157":0.0,"160":0.0,"99":0.0,"102":0.0,"18":0.0,"24":0.0,"105":0.0,"21":0.0,"72":0.0,"159":0.0,"153":0.0,"156":0.0,"75":0.0,"78":0.0,"104":0.0,"26":0.0,"20":0.0,"101":0.0,"107":0.0,"23":0.0,"19":0.0,"22":0.0,"103":0.0,"100":0.0,"106":0.0,"25":0.0,"134":0.0,"53":0.0,"131":0.0,"47":0.0,"50":0.0,"128":0.0,"46":0.0,"52":0.0,"129":0.0,"126":0.0,"45":0.0,"48":0.0,"49":0.0,"51":0.0,"127":0.0,"130":0.0,"132":0.0,"133":0.0},"nodes":{"32":34,"113":34,"38":34,"122":34,"44":34,"29":34,"41":34,"35":34,"125":34,"119":34,"110":34,"116":34,"118":44,"33":44,"42":44,"121":44,"39":44,"36":44,"37":44,"27":44,"115":44,"112":44,"111":44,"28":44,"34":44,"40":44,"124":44,"123":44,"120":44,"30":44,"114":44,"109":44,"43":44,"31":44,"117":44,"108":44,"91":52,"13":52,"88":52,"82":52,"84":52,"97":52,"93":52,"12":52,"81":52,"85":52,"10":52,"16":52,"96":52,"94":52,"90":52,"15":52,"7":52,"87":52,"9":52,"4":52,"6":52,"1":52,"3":52,"86":77,"2":77,"98":77,"5":77,"17":77,"83":77,"89":77,"95":77,"92":77,"14":77,"11":77,"8":77,"0":52,"71":131,"137":131,"152":131,"65":131,"68":131,"59":131,"140":131,"149":131,"146":131,"56":131,"143":131,"62":131,"63":181,"135":181,"58":181,"148":181,"138":181,"151":181,"64":181,"141":181,"139":181,"54":181,"57":181,"147":181,"69":181,"66":181,"61":181,"144":181,"145":181,"136":181,"67":181,"142":181,"150":181,"60":181,"70":181,"55":181,"77":10,"80":10,"158":10,"74":10,"73":20,"154":20,"76":20,"79":20,"161":10,"155":10,"157":20,"160":20,"99":63,"102":63,"18":63,"24":63,"105":63,"21":63,"72":24,"159":24,"153":24,"156":24,"75":24,"78":24,"104":59,"26":59,"20":59,"101":59,"107":59,"23":59,"19":88,"22":88,"103":88,"100":88,"106":88,"25":88,"134":95,"53":95,"131":95,"47":95,"50":95,"128":95,"46":107,"52":107,"129":107,"126":107,"45":107,"48":107,"49":107,"51":107,"127":107,"130":107,"132":107,"133":107},"time_mean":{"32":0.4562333333,"113":0.4567666667,"38":0.4579,"122":0.4583333333,"44":0.4588,"29":0.4588333333,"41":0.4589333333,"35":0.459,"125":0.4593333333,"119":0.4598666667,"110":0.4604666667,"116":0.4618,"118":0.4634666667,"33":0.4639666667,"42":0.4640666667,"121":0.4645333333,"39":0.4645666667,"36":0.4646333333,"37":0.4650333333,"27":0.4651,"115":0.4651666667,"112":0.4651666667,"111":0.4656,"28":0.4656333333,"34":0.4656333333,"40":0.4656666667,"124":0.4656666667,"123":0.4657,"120":0.4661333333,"30":0.4661333333,"114":0.4661666667,"109":0.4667,"43":0.4667333333,"31":0.4687,"117":0.4708333333,"108":0.4708666667,"91":0.4823333333,"13":0.4833666667,"88":0.4836666667,"82":0.4842333333,"84":0.4843666667,"97":0.4847333333,"93":0.4848666667,"12":0.4849333333,"81":0.4853,"85":0.4856,"10":0.4856333333,"16":0.4861333333,"96":0.4863,"94":0.4863666667,"90":0.4868333333,"15":0.4870333333,"7":0.4870666667,"87":0.4874666667,"9":0.4876,"4":0.4876333333,"6":0.4878333333,"1":0.4880666667,"3":0.4901333333,"86":0.5166666667,"2":0.5167333333,"98":0.5176666667,"5":0.5181333333,"17":0.5183333333,"83":0.5188666667,"89":0.5192666667,"95":0.5197333333,"92":0.5198333333,"14":0.5209333333,"11":0.5213333333,"8":0.5219333333,"0":0.5346,"71":0.7209,"137":0.7212666667,"152":0.7218333333,"65":0.7219333333,"68":0.7224333333,"59":0.7229,"140":0.7229333333,"149":0.7233666667,"146":0.7256,"56":0.7259,"143":0.7274,"62":0.7308333333,"63":0.7359333333,"135":0.7371,"58":0.7371666667,"148":0.7374333333,"138":0.7376,"151":0.7379333333,"64":0.7391333333,"141":0.7394333333,"139":0.7400333333,"54":0.7400666667,"57":0.7405,"147":0.7406,"69":0.7407333333,"66":0.7411666667,"61":0.7417666667,"144":0.7417666667,"145":0.7419,"136":0.7421333333,"67":0.7421333333,"142":0.7422666667,"150":0.7433,"60":0.7441333333,"70":0.7458333333,"55":0.7468666667,"77":1.1207666667,"80":1.1219333333,"158":1.1229333333,"74":1.1250333333,"73":1.1266,"154":1.1266,"76":1.1286,"79":1.1290666667,"161":1.1291333333,"155":1.1297666667,"157":1.1339,"160":1.136,"99":1.1578666667,"102":1.1596,"18":1.1605,"24":1.1619,"105":1.1631666667,"21":1.1671,"72":1.1771333333,"159":1.1777333333,"153":1.179,"156":1.1822,"75":1.1826666667,"78":1.1843333333,"104":1.2709666667,"26":1.2724333333,"20":1.2755,"101":1.2765,"107":1.2785333333,"23":1.2801666667,"19":1.2833333333,"22":1.2843666667,"103":1.2851,"100":1.2879,"106":1.2891,"25":1.2891333333,"134":1.3241,"53":1.3246,"131":1.3251,"47":1.3256,"50":1.3280666667,"128":1.3297,"46":1.3316333333,"52":1.3317333333,"129":1.3338666667,"126":1.3342,"45":1.3348,"48":1.3355,"49":1.3364333333,"51":1.337,"127":1.337,"130":1.3370666667,"132":1.3374666667,"133":1.3374666667},"time_std":{"32":0.0063070507,"113":0.0066014308,"38":0.0083640102,"122":0.0094880041,"44":0.0094987719,"29":0.007536946,"41":0.0085281234,"35":0.0075498344,"125":0.010358035,"119":0.0087014686,"110":0.0097902446,"116":0.0086810138,"118":0.0073427213,"33":0.0081054851,"42":0.008225705,"121":0.0079696647,"39":0.0098916912,"36":0.0098673986,"37":0.0087919787,"27":0.0076609399,"115":0.0096023724,"112":0.0087866692,"111":0.0109987878,"28":0.0101537623,"34":0.0094427515,"40":0.0085647858,"124":0.00950906,"123":0.0084543874,"120":0.0081024002,"30":0.0090948093,"114":0.0091034182,"109":0.0076817967,"43":0.0105985324,"31":0.0134738017,"117":0.0244063972,"108":0.0138196318,"91":0.0078542275,"13":0.0088862566,"88":0.0056174332,"82":0.0120545519,"84":0.0089572441,"97":0.0075671806,"93":0.007632096,"12":0.0075583655,"81":0.0080421805,"85":0.0088904443,"10":0.0069305283,"16":0.0068299992,"96":0.0053860932,"94":0.0096867034,"90":0.010050152,"15":0.0092212918,"7":0.0080412824,"87":0.0094082706,"9":0.0093116415,"4":0.0124378008,"6":0.0119305863,"1":0.0117726614,"3":0.0141674117,"86":0.0090012345,"2":0.0106236633,"98":0.0096793021,"5":0.0090764653,"17":0.0116026817,"83":0.0061629719,"89":0.0096018517,"95":0.0107049314,"92":0.0089817717,"14":0.0110542099,"11":0.0093464194,"8":0.0136062077,"0":0.0703806792,"71":0.0113529732,"137":0.0090955423,"152":0.009398877,"65":0.0063819189,"68":0.0067905981,"59":0.0088932559,"140":0.007987212,"149":0.0081669388,"146":0.0138361844,"56":0.011073542,"143":0.0096041658,"62":0.0112252196,"63":0.009398345,"135":0.0081582269,"58":0.0098559063,"148":0.0094751722,"138":0.010031949,"151":0.0066679999,"64":0.0108619622,"141":0.0101970039,"139":0.0118250675,"54":0.0103631827,"57":0.0118483473,"147":0.0110953444,"69":0.0142710274,"66":0.0131911165,"61":0.0143426714,"144":0.0118565969,"145":0.0111664677,"136":0.0104904189,"67":0.0118764005,"142":0.0096434203,"150":0.0143204981,"60":0.0124331099,"70":0.0098457549,"55":0.0234403261,"77":0.009817275,"80":0.0073978976,"158":0.014903989,"74":0.0080725185,"73":0.0101574275,"154":0.0108246632,"76":0.0111253464,"79":0.0098350846,"161":0.0169818203,"155":0.0135392844,"157":0.0184162066,"160":0.0134585784,"99":0.0117295448,"102":0.0124032254,"18":0.0113276947,"24":0.0147746404,"105":0.0174127986,"21":0.014561021,"72":0.0101971674,"159":0.0103985042,"153":0.0131681434,"156":0.0128150953,"75":0.0193758154,"78":0.0142672897,"104":0.0116946807,"26":0.0119852224,"20":0.0101743141,"101":0.0122358762,"107":0.0151321585,"23":0.0327608337,"19":0.0111843144,"22":0.0137246332,"103":0.0077,"100":0.0104126526,"106":0.0131005089,"25":0.0131978113,"134":0.0150096636,"53":0.0118900519,"131":0.0109036691,"47":0.0134228661,"50":0.0190226765,"128":0.0110004545,"46":0.0123894669,"52":0.0096365047,"129":0.0111167541,"126":0.0118276512,"45":0.0137753403,"48":0.0119770614,"49":0.0111972715,"51":0.0119247641,"127":0.0117926531,"130":0.0125722799,"132":0.0129967517,"133":0.0137106609},"time_var":{"32":0.0000397789,"113":0.0000435789,"38":0.0000699567,"122":0.0000900222,"44":0.0000902267,"29":0.0000568056,"41":0.0000727289,"35":0.000057,"125":0.0001072889,"119":0.0000757156,"110":0.0000958489,"116":0.00007536,"118":0.0000539156,"33":0.0000656989,"42":0.0000676622,"121":0.0000635156,"39":0.0000978456,"36":0.0000973656,"37":0.0000772989,"27":0.00005869,"115":0.0000922056,"112":0.0000772056,"111":0.0001209733,"28":0.0001030989,"34":0.0000891656,"40":0.0000733556,"124":0.0000904222,"123":0.0000714767,"120":0.0000656489,"30":0.0000827156,"114":0.0000828722,"109":0.00005901,"43":0.0001123289,"31":0.0001815433,"117":0.0005956722,"108":0.0001909822,"91":0.0000616889,"13":0.0000789656,"88":0.0000315556,"82":0.0001453122,"84":0.0000802322,"97":0.0000572622,"93":0.0000582489,"12":0.0000571289,"81":0.0000646767,"85":0.00007904,"10":0.0000480322,"16":0.0000466489,"96":0.00002901,"94":0.0000938322,"90":0.0001010056,"15":0.0000850322,"7":0.0000646622,"87":0.0000885156,"9":0.0000867067,"4":0.0001546989,"6":0.0001423389,"1":0.0001385956,"3":0.0002007156,"86":0.0000810222,"2":0.0001128622,"98":0.0000936889,"5":0.0000823822,"17":0.0001346222,"83":0.0000379822,"89":0.0000921956,"95":0.0001145956,"92":0.0000806722,"14":0.0001221956,"11":0.0000873556,"8":0.0001851289,"0":0.00495344,"71":0.00012889,"137":0.0000827289,"152":0.0000883389,"65":0.0000407289,"68":0.0000461122,"59":0.00007909,"140":0.0000637956,"149":0.0000666989,"146":0.00019144,"56":0.0001226233,"143":0.00009224,"62":0.0001260056,"63":0.0000883289,"135":0.0000665567,"58":0.0000971389,"148":0.0000897789,"138":0.00010064,"151":0.0000444622,"64":0.0001179822,"141":0.0001039789,"139":0.0001398322,"54":0.0001073956,"57":0.0001403833,"147":0.0001231067,"69":0.0002036622,"66":0.0001740056,"61":0.0002057122,"144":0.0001405789,"145":0.00012469,"136":0.0001100489,"67":0.0001410489,"142":0.0000929956,"150":0.0002050767,"60":0.0001545822,"70":0.0000969389,"55":0.0005494489,"77":0.0000963789,"80":0.0000547289,"158":0.0002221289,"74":0.0000651656,"73":0.0001031733,"154":0.0001171733,"76":0.0001237733,"79":0.0000967289,"161":0.0002883822,"155":0.0001833122,"157":0.0003391567,"160":0.0001811333,"99":0.0001375822,"102":0.00015384,"18":0.0001283167,"24":0.00021829,"105":0.0003032056,"21":0.0002120233,"72":0.0001039822,"159":0.0001081289,"153":0.0001734,"156":0.0001642267,"75":0.0003754222,"78":0.0002035556,"104":0.0001367656,"26":0.0001436456,"20":0.0001035167,"101":0.0001497167,"107":0.0002289822,"23":0.0010732722,"19":0.0001250889,"22":0.0001883656,"103":0.00005929,"100":0.0001084233,"106":0.0001716233,"25":0.0001741822,"134":0.00022529,"53":0.0001413733,"131":0.00011889,"47":0.0001801733,"50":0.0003618622,"128":0.00012101,"46":0.0001534989,"52":0.0000928622,"129":0.0001235822,"126":0.0001398933,"45":0.00018976,"48":0.00014345,"49":0.0001253789,"51":0.0001422,"127":0.0001390667,"130":0.0001580622,"132":0.0001689156,"133":0.0001879822}}